adc_hdl/adc_fsm_10b_real/ideal_comparator_10b.v
module ideal_comparator_10b(  vip, 
                              vin, 
                              comp_result, 
                              comp_done, 
                              clk, 
                              rst);
   
   input [9:0] vip, vin;
   input clk, rst;
   output reg comp_result, comp_done;

   always @ (posedge clk) begin
      if (!comp_done) begin
         comp_result <= (vip >= vin);
         comp_done <= 1;
      end
   end
   
   always @ (negedge clk or rst) begin
      comp_result <= 0;
      comp_done <= 0;
   end
   
endmodule

adc_hdl/adc_fsm_10b_real/adc_fsm_10b_v1.v
// Adapted from http://math-crunching.blogspot.com/2015/12/sar-logic-verilog-hdl-code.html
// YYK: converted into sort of asynchronous circuit
// implemented as a state machine
// 30th december 2019

`timescale 100ns/1ns

module adc_fsm_10b_v1(  st_conv,
                        clkout,
                        clkin,
                        sample,
                        result,
                        dac_value,
                        dac_msb,
                        dac_lsb,
                        comp_in,
                        adc_done,
                        rst,
                        sel_12b,
                        cal);
                        
   input  st_conv;         // positive edge starts sampling, negative edge starts conversion
   output clkout;          // clock output to comparator
   input  clkin;           // clock input from comparator
   output sample;          // to S&H switch. Active high
   output [9:0] result;    // final result
   output [9:0] dac_value; // value to feed DAC
   output [9:5] dac_msb;   // value for DAC MSB array
   output [4:0] dac_lsb;   // value for DAC LSB array
   input comp_in;          // comparator result
   output adc_done;        // done=1 when conversion finishes
   input rst;              // for resetting the fsm
   input sel_12b;          // for selecting 12 steps or 10 steps. High means choose 12.
   input cal;              // for calibrating out ADC comparator offset
   
   reg [9:0] offset;          // For storing comparator offset
   wire clkout;               // clock output to comparator
   // Internal variables and registers
   reg [1:0] state;           // current state in state machine
   reg [9:0] result;         // final ADC answer
   reg [3:0] pointer;         // pointer for the search algo to index the steps
   reg [9:0] steps [11:0];   // array to store step sizes. 10-bit wide steps with depth of 12 steps
   reg [3:0] defaultpointer;  // default pointer to index the ADC steps
   
   // state assignment
   parameter sWait=0, sSample=1, sConv=2, sDone=3;   
   
   // Initialize the step sizes based on T.Ogawa's 2010 paper
   always @ (posedge rst) begin
      if (sel_12b==1) begin
         steps[11] <= 10'd512;
         steps[10] <= 10'd246;
         steps[9]  <= 10'd113;
         steps[8]  <= 10'd65;
         steps[7]  <= 10'd37;
         steps[6]  <= 10'd21;
         steps[5]  <= 10'd13;
         steps[4]  <= 10'd7;
         steps[3]  <= 10'd4;
         steps[2]  <= 10'd2;
         steps[1]  <= 10'd2;
         steps[0]  <= 10'd1;
         defaultpointer <= 4'd11;
      end
      else begin
         steps[11]<= 10'd512;
         steps[10]<= 10'd512;
         steps[9] <= 10'd512;
         steps[8] <= 10'd256;
         steps[7] <= 10'd128;
         steps[6] <= 10'd64;
         steps[5] <= 10'd32;
         steps[4] <= 10'd16;
         steps[3] <= 10'd8;
         steps[2] <= 10'd4;
         steps[1] <= 10'd2;
         steps[0] <= 10'd1;
         defaultpointer <= 4'd9;
      end
      state    <= sWait;
      result   <= 0;
      offset   <= 10'd0;
      pointer  <= 0;
   end
   
   always @ (posedge st_conv) begin
      // If st_conv goes high, start the sampling switch
      state    <= sSample;
      pointer  <= defaultpointer;
      if (cal)
         result   <= 10'b0;
      else
         result   <= 10'b0 - offset;
   end
   
   always @ (negedge st_conv) begin
      // If st_conv has a falling edge, start the conversion
      state    <= sConv;
      result   <= 10'b0;
   end
   
   // synchronous design
   always @(posedge clkin) begin
   case (state) // choose next state in state machine
      sConv :
         begin
            // clkout <= 0;
            if (comp_in) 
               result <= result + steps[pointer];
            
            // finished once LSB has been done
            if (pointer==0)  begin
               state    <= sDone;
               pointer  <= pointer;
               if (cal) begin
                  //offset <= (result + (steps[pointer] && comp_in)) - 10'd512 ;
                  offset <= 10'd512 - (result + (steps[pointer] && comp_in));
               end
            end
            else begin
               state    <= sConv;
               pointer  <= pointer - 1;
            end
         end
      sDone :   state   <= sWait;
      default : state   <= sWait;
   endcase
   end
   
   assign clkout = (!clkin & (state==sConv));
   assign sample = (state==sSample);  // drive sample and hold
   assign dac_value = result + steps[pointer]; // to drive DAC
   assign dac_lsb[4:0] = dac_value[4:0];
   assign dac_msb[9:5] = 5'd31 - dac_value[9:5];
   assign adc_done = state==sDone;  // indicate when finished

endmodule

adc_hdl/adc_fsm_10b_real/testbench_adc_fsm_12s.v
`timescale 100ns/1ns

module testbench_adc_fsm_12s;
   
   wire fire_comp1, comp_done1, comp_result1, sample1, adc_done1;
   wire fire_comp2, comp_done2, comp_result2, sample2, adc_done2;
   wire [9:0] dac_value1, result1;
   wire [9:0] dac_value2, result2;
   reg  [9:0] reference = 0;
   
   reg delayed_comp_done1=0;
   reg delayed_comp_done2=0;
   reg delayed_comp_result1=0;
   reg delayed_comp_result2=0;
   reg delayed_fire_comp1=0;
   reg delayed_fire_comp2=0;
   reg st_conv, rst;
   
   reg [12:0] index = 0;      // Loop counter
   reg [12:0] innerindex = 0; // Inner loop counter
   reg [11:0] summary_results1;
   reg [11:0] summary_results2;
   
   integer textfile1 = 0;
   
   always @(comp_done1) delayed_comp_done1 <= #1 comp_done1;
   always @(comp_done2) delayed_comp_done2 <= #1 comp_done2;
   
   always @(comp_result1) delayed_comp_result1 <= #0.5 comp_result1;
   always @(comp_result2) delayed_comp_result2 <= #0.5 comp_result2;
   
   always @(fire_comp1) delayed_fire_comp1 <= #0.5 fire_comp1;
   always @(fire_comp2) delayed_fire_comp2 <= #0.5 fire_comp2;
   
   adc_fsm_10b_v1 adc1( .st_conv(st_conv),
                        .clkout(fire_comp1),
                        .clkin(delayed_comp_done1),
                        .sample(),
                        .result(result1),
                        .dac_value(dac_value1),
                        .dac_msb(),
                        .dac_lsb(),
                        .comp_in(delayed_comp_result1),
                        .adc_done(adc_done1),
                        .rst(rst),
                        .sel_12b(1'b0),
                        .cal(1'b0));

   ideal_comparator_10b comp1(.vip(reference), 
                              .vin(dac_value1), 
                              .comp_result(comp_result1), 
                              .comp_done(comp_done1), 
                              .clk(delayed_fire_comp1), 
                              .rst(rst));
   
   adc_fsm_10b_v1 adc2( .st_conv(st_conv),
                        .clkout(fire_comp2),
                        .clkin(delayed_comp_done2),
                        .sample(),
                        .result(result2),
                        .dac_value(dac_value2),
                        .dac_msb(),
                        .dac_lsb(),
                        .comp_in(delayed_comp_result2),
                        .adc_done(adc_done2),
                        .rst(rst),
                        .sel_12b(1'b1),
                        .cal(1'b0));
                           
   ideal_comparator_10b comp2(.vip(reference), 
                              .vin(dac_value2), 
                              .comp_result(comp_result2), 
                              .comp_done(comp_done2), 
                              .clk(delayed_fire_comp2), 
                              .rst(rst));
   
   always @ (posedge adc_done1 or posedge rst) begin
      if (rst) 
         summary_results1 <= 0;
      else
         summary_results1 <= result1;
   end
   
   always @ (posedge adc_done2 or posedge rst) begin
      if (rst) 
         summary_results2 <= 0;
      else
         summary_results2 <= result2;
   end
   
   initial begin
      st_conv = 0;
      rst = 0;
      textfile1 = $fopen("adc_ecc.csv","w");
      $fwrite(textfile1,"ref,adc1,adc2,\n");
      $dumpfile("log.vcd");
		$dumpvars;
      #1 rst = 0;
      #1 rst = 1;
      #1 rst = 0;
      
      for (index=0; index<1024; index = index + 1) begin
         for (innerindex=0;innerindex<1; innerindex = innerindex+1) begin
            #1 st_conv = 1;
            #1 st_conv = 0;
            #40 $fwrite(textfile1,"%d,%d,%d\n",reference,summary_results1,summary_results2);
         end
         reference = reference + 1;
      end
      
      #1 $fclose(textfile1);
      #10 $finish;
   end

endmodule

adc_hdl/adc_fsm_10b_real/samplehold.v
`timescale 100ns/1ns

module samplehold(vin, sample, vout);
   
   input sample;
   input [9:0] vin; 
   output [11:0] vout;
   
   reg [11:0] vin_se;
   reg [11:0] stored_value;
   
   always @ * begin
      vin_se <= {2'b0, vin[9:0]};
   end
   
   always @ (negedge sample) begin
      stored_value <= 12'd512 - vin_se;
   end
   
   always @ (posedge sample) begin
      stored_value <= 12'd0;
   end
   
   assign vout = $signed(vin_se) - $signed(stored_value);
   
endmodule

adc_hdl/adc_fsm_10b_real/conditional_offset.v
module conditional_offset( vin, 
                           vout,
                           offset);

   input [9:0] vin, offset;
   output [9:0] vout;
   
   reg [9:0] vout;
   reg [9:0] flipped_offset;
   
   always @ (*) begin
      flipped_offset = ~offset + 10'd1;
      
      if (offset[9]) begin // if negative number
         if (vin > flipped_offset)
            vout = vin - flipped_offset;
         else
            vout = 10'd0;  // set a floor at 0
      end
      else begin           // if positive number
         if (vin < (10'd 1023 - offset))
            vout = vin + offset;
         else
            vout = 10'd1023;
      end
   end
endmodule

adc_hdl/adc_fsm_10b_real/log.vcd
$date
	Fri Jan 10 17:02:52 2020
$end
$version
	Icarus Verilog
$end
$timescale
	1ns
$end
$scope module conditional_offset $end
$var wire 10 ! offset [9:0] $end
$var wire 10 " vin [9:0] $end
$var reg 10 # flipped_offset [9:0] $end
$var reg 10 $ vout [9:0] $end
$upscope $end
$scope module samplehold $end
$var wire 1 % sample $end
$var wire 10 & vin [9:0] $end
$var wire 12 ' vout [11:0] $end
$var reg 12 ( stored_value [11:0] $end
$var reg 12 ) vin_se [11:0] $end
$upscope $end
$scope module testbench_adc_fsm_12s $end
$var wire 10 * result2 [9:0] $end
$var wire 10 + result1 [9:0] $end
$var wire 1 , fire_comp2 $end
$var wire 1 - fire_comp1 $end
$var wire 10 . dac_value2 [9:0] $end
$var wire 10 / dac_value1 [9:0] $end
$var wire 1 0 comp_result2 $end
$var wire 1 1 comp_result1 $end
$var wire 1 2 comp_done2 $end
$var wire 1 3 comp_done1 $end
$var wire 1 4 adc_done2 $end
$var wire 1 5 adc_done1 $end
$var reg 1 6 delayed_comp_done1 $end
$var reg 1 7 delayed_comp_done2 $end
$var reg 1 8 delayed_comp_result1 $end
$var reg 1 9 delayed_comp_result2 $end
$var reg 1 : delayed_fire_comp1 $end
$var reg 1 ; delayed_fire_comp2 $end
$var reg 13 < index [12:0] $end
$var reg 13 = innerindex [12:0] $end
$var reg 10 > reference [9:0] $end
$var reg 1 ? rst $end
$var reg 1 @ st_conv $end
$var reg 12 A summary_results1 [11:0] $end
$var reg 12 B summary_results2 [11:0] $end
$var integer 32 C textfile1 [31:0] $end
$scope module adc1 $end
$var wire 1 D cal $end
$var wire 1 6 clkin $end
$var wire 1 - clkout $end
$var wire 1 8 comp_in $end
$var wire 1 ? rst $end
$var wire 1 E sel_12b $end
$var wire 1 @ st_conv $end
$var wire 1 F sample $end
$var wire 10 G dac_value [9:0] $end
$var wire 5 H dac_msb [9:5] $end
$var wire 5 I dac_lsb [4:0] $end
$var wire 1 5 adc_done $end
$var reg 4 J defaultpointer [3:0] $end
$var reg 10 K offset [9:0] $end
$var reg 4 L pointer [3:0] $end
$var reg 10 M result [9:0] $end
$var reg 2 N state [1:0] $end
$upscope $end
$scope module adc2 $end
$var wire 1 O cal $end
$var wire 1 7 clkin $end
$var wire 1 , clkout $end
$var wire 1 9 comp_in $end
$var wire 1 ? rst $end
$var wire 1 P sel_12b $end
$var wire 1 @ st_conv $end
$var wire 1 Q sample $end
$var wire 10 R dac_value [9:0] $end
$var wire 5 S dac_msb [9:5] $end
$var wire 5 T dac_lsb [4:0] $end
$var wire 1 4 adc_done $end
$var reg 4 U defaultpointer [3:0] $end
$var reg 10 V offset [9:0] $end
$var reg 4 W pointer [3:0] $end
$var reg 10 X result [9:0] $end
$var reg 2 Y state [1:0] $end
$upscope $end
$scope module comp1 $end
$var wire 1 : clk $end
$var wire 1 ? rst $end
$var wire 10 Z vin [9:0] $end
$var wire 10 [ vip [9:0] $end
$var reg 1 3 comp_done $end
$var reg 1 1 comp_result $end
$upscope $end
$scope module comp2 $end
$var wire 1 ; clk $end
$var wire 1 ? rst $end
$var wire 10 \ vin [9:0] $end
$var wire 10 ] vip [9:0] $end
$var reg 1 2 comp_done $end
$var reg 1 0 comp_result $end
$upscope $end
$upscope $end
$enddefinitions $end
#0
$dumpvars
b0 ]
bx \
b0 [
bx Z
b10 Y
b0 X
bx W
bx V
bx U
bx T
bx S
bx R
0Q
1P
0O
b10 N
b0 M
bx L
bx K
bx J
bx I
bx H
bx G
0F
0E
0D
b10000000000000000000000000000011 C
bx B
bx A
0@
0?
b0 >
b0 =
b0 <
0;
0:
09
08
07
06
05
04
03
02
01
00
bx /
bx .
1-
1,
b0 +
b0 *
b0zzzzzzzzzz )
bx (
bx '
bz &
z%
b1111111111 $
bx #
bz "
bz !
$end
#50
13
x1
12
x0
1:
1;
#100
x8
x9
#150
0-
0,
16
17
#200
b1 I
b11111 H
b1 T
b11111 S
b1 /
b1 G
b1 Z
b0 L
b0 K
b0 N
b1001 J
b1 .
b1 R
b1 \
b0 W
b0 V
b0 Y
b1011 U
03
01
02
00
b0 A
b0 B
0:
0;
1?
#250
08
09
#300
06
07
0?
#400
b0 I
b1111 H
b0 T
b1111 S
b1000000000 /
b1000000000 G
b1000000000 Z
b1001 L
1F
b1 N
b1000000000 .
b1000000000 R
b1000000000 \
b1011 W
1Q
b1 Y
1@
#500
1,
1-
0Q
b10 Y
0F
b10 N
0@
#550
12
13
1;
1:
#650
b10110 T
b11000 S
b10111 H
b11110110 .
b11110110 R
b11110110 \
b1010 W
b100000000 /
b100000000 G
b100000000 Z
b1000 L
0,
0-
17
16
#700
02
03
0;
0:
#800
1,
1-
07
06
#850
12
13
1;
1:
#950
b10001 T
b11100 S
b11011 H
b1110001 .
b1110001 R
b1110001 \
b1001 W
b10000000 /
b10000000 G
b10000000 Z
b111 L
0,
0-
17
16
#1000
02
03
0;
0:
#1100
1,
1-
07
06
#1150
12
13
1;
1:
#1250
b1 T
b11101 S
b11101 H
b1000001 .
b1000001 R
b1000001 \
b1000 W
b1000000 /
b1000000 G
b1000000 Z
b110 L
0,
0-
17
16
#1300
02
03
0;
0:
#1400
1,
1-
07
06
#1450
12
13
1;
1:
#1550
b101 T
b11110 S
b11110 H
b100101 .
b100101 R
b100101 \
b111 W
b100000 /
b100000 G
b100000 Z
b101 L
0,
0-
17
16
#1600
02
03
0;
0:
#1700
1,
1-
07
06
#1750
12
13
1;
1:
#1850
b10101 T
b11111 S
b10000 I
b11111 H
b10101 .
b10101 R
b10101 \
b110 W
b10000 /
b10000 G
b10000 Z
b100 L
0,
0-
17
16
#1900
02
03
0;
0:
#2000
1,
1-
07
06
#2050
12
13
1;
1:
#2150
b1101 T
b1000 I
b1101 .
b1101 R
b1101 \
b101 W
b1000 /
b1000 G
b1000 Z
b11 L
0,
0-
17
16
#2200
02
03
0;
0:
#2300
1,
1-
07
06
#2350
12
13
1;
1:
#2450
b111 T
b100 I
b111 .
b111 R
b111 \
b100 W
b100 /
b100 G
b100 Z
b10 L
0,
0-
17
16
#2500
02
03
0;
0:
#2600
1,
1-
07
06
#2650
12
13
1;
1:
#2750
b100 T
b10 I
b100 .
b100 R
b100 \
b11 W
b10 /
b10 G
b10 Z
b1 L
0,
0-
17
16
#2800
02
03
0;
0:
#2900
1,
1-
07
06
#2950
12
13
1;
1:
#3050
b10 T
b1 I
b10 .
b10 R
b10 \
b10 W
b1 /
b1 G
b1 Z
b0 L
0,
0-
17
16
#3100
02
03
0;
0:
#3200
1,
1-
07
06
#3250
12
13
1;
1:
#3350
b1 W
15
b11 N
0,
0-
17
16
#3400
02
03
0;
0:
#3500
1,
07
06
#3550
12
1;
#3650
b1 T
b1 .
b1 R
b1 \
b0 W
0,
17
#3700
02
0;
#3800
1,
07
#3850
12
1;
#3950
14
b11 Y
0,
17
#4000
02
0;
#4100
07
#4500
b1 <
b1 >
b1 [
b1 ]
b0 =
#4600
b0 T
b1111 S
b0 I
b1111 H
b1000000000 .
b1000000000 R
b1000000000 \
b1011 W
1Q
04
b1 Y
b1000000000 /
b1000000000 G
b1000000000 Z
b1001 L
1F
05
b1 N
1@
#4700
1-
1,
0F
b10 N
0Q
b10 Y
0@
#4750
13
12
1:
1;
#4850
b10111 H
b10110 T
b11000 S
b100000000 /
b100000000 G
b100000000 Z
b1000 L
b11110110 .
b11110110 R
b11110110 \
b1010 W
0-
0,
16
17
#4900
03
02
0:
0;
#5000
1-
1,
06
07
#5050
13
12
1:
1;
#5150
b11011 H
b10001 T
b11100 S
b10000000 /
b10000000 G
b10000000 Z
b111 L
b1110001 .
b1110001 R
b1110001 \
b1001 W
0-
0,
16
17
#5200
03
02
0:
0;
#5300
1-
1,
06
07
#5350
13
12
1:
1;
#5450
b11101 H
b1 T
b11101 S
b1000000 /
b1000000 G
b1000000 Z
b110 L
b1000001 .
b1000001 R
b1000001 \
b1000 W
0-
0,
16
17
#5500
03
02
0:
0;
#5600
1-
1,
06
07
#5650
13
12
1:
1;
#5750
b11110 H
b101 T
b11110 S
b100000 /
b100000 G
b100000 Z
b101 L
b100101 .
b100101 R
b100101 \
b111 W
0-
0,
16
17
#5800
03
02
0:
0;
#5900
1-
1,
06
07
#5950
13
12
1:
1;
#6050
b10000 I
b11111 H
b10101 T
b11111 S
b10000 /
b10000 G
b10000 Z
b100 L
b10101 .
b10101 R
b10101 \
b110 W
0-
0,
16
17
#6100
03
02
0:
0;
#6200
1-
1,
06
07
#6250
13
12
1:
1;
#6350
b1000 I
b1101 T
b1000 /
b1000 G
b1000 Z
b11 L
b1101 .
b1101 R
b1101 \
b101 W
0-
0,
16
17
#6400
03
02
0:
0;
#6500
1-
1,
06
07
#6550
13
12
1:
1;
#6650
b100 I
b111 T
b100 /
b100 G
b100 Z
b10 L
b111 .
b111 R
b111 \
b100 W
0-
0,
16
17
#6700
03
02
0:
0;
#6800
1-
1,
06
07
#6850
13
12
1:
1;
#6950
b10 I
b100 T
b10 /
b10 G
b10 Z
b1 L
b100 .
b100 R
b100 \
b11 W
0-
0,
16
17
#7000
03
02
0:
0;
#7100
1-
1,
06
07
#7150
13
12
1:
1;
#7250
b1 I
b10 T
b1 /
b1 G
b1 Z
b0 L
b10 .
b10 R
b10 \
b10 W
0-
0,
16
17
#7300
03
02
0:
0;
#7400
1-
1,
06
07
#7450
13
11
12
1:
1;
#7500
18
#7550
b1 A
b10 I
15
b11 N
b10 /
b10 G
b10 Z
b1 +
b1 M
b1 W
0-
0,
16
17
#7600
03
01
02
0:
0;
#7650
08
#7700
1,
06
07
#7750
12
1;
#7850
b1 T
b1 .
b1 R
b1 \
b0 W
0,
17
#7900
02
0;
#8000
1,
07
#8050
12
10
1;
#8100
19
#8150
b1 B
b10 T
14
b11 Y
b10 .
b10 R
b10 \
b1 *
b1 X
0,
17
#8200
02
00
0;
#8250
09
#8300
07
#8700
b10 <
b10 >
b10 [
b10 ]
b0 =
#8800
b0 I
b1111 H
b0 T
b1111 S
b0 +
b0 M
b1000000000 /
b1000000000 G
b1000000000 Z
b1001 L
1F
05
b1 N
b0 *
b0 X
b1000000000 .
b1000000000 R
b1000000000 \
b1011 W
1Q
04
b1 Y
1@
#8900
1,
1-
0Q
b10 Y
0F
b10 N
0@
#8950
12
13
1;
1:
#9050
b10110 T
b11000 S
b10111 H
b11110110 .
b11110110 R
b11110110 \
b1010 W
b100000000 /
b100000000 G
b100000000 Z
b1000 L
0,
0-
17
16
#9100
02
03
0;
0:
#9200
1,
1-
07
06
#9250
12
13
1;
1:
#9350
b10001 T
b11100 S
b11011 H
b1110001 .
b1110001 R
b1110001 \
b1001 W
b10000000 /
b10000000 G
b10000000 Z
b111 L
0,
0-
17
16
#9400
02
03
0;
0:
#9500
1,
1-
07
06
#9550
12
13
1;
1:
#9650
b1 T
b11101 S
b11101 H
b1000001 .
b1000001 R
b1000001 \
b1000 W
b1000000 /
b1000000 G
b1000000 Z
b110 L
0,
0-
17
16
#9700
02
03
0;
0:
#9800
1,
1-
07
06
#9850
12
13
1;
1:
#9950
b101 T
b11110 S
b11110 H
b100101 .
b100101 R
b100101 \
b111 W
b100000 /
b100000 G
b100000 Z
b101 L
0,
0-
17
16
#10000
02
03
0;
0:
#10100
1,
1-
07
06
#10150
12
13
1;
1:
#10250
b10101 T
b11111 S
b10000 I
b11111 H
b10101 .
b10101 R
b10101 \
b110 W
b10000 /
b10000 G
b10000 Z
b100 L
0,
0-
17
16
#10300
02
03
0;
0:
#10400
1,
1-
07
06
#10450
12
13
1;
1:
#10550
b1101 T
b1000 I
b1101 .
b1101 R
b1101 \
b101 W
b1000 /
b1000 G
b1000 Z
b11 L
0,
0-
17
16
#10600
02
03
0;
0:
#10700
1,
1-
07
06
#10750
12
13
1;
1:
#10850
b111 T
b100 I
b111 .
b111 R
b111 \
b100 W
b100 /
b100 G
b100 Z
b10 L
0,
0-
17
16
#10900
02
03
0;
0:
#11000
1,
1-
07
06
#11050
12
13
1;
1:
#11150
b100 T
b10 I
b100 .
b100 R
b100 \
b11 W
b10 /
b10 G
b10 Z
b1 L
0,
0-
17
16
#11200
02
03
0;
0:
#11300
1,
1-
07
06
#11350
12
13
11
1;
1:
#11400
18
#11450
b10 T
b11 I
b10 .
b10 R
b10 \
b10 W
b0 L
b11 /
b11 G
b11 Z
b10 +
b10 M
0,
0-
17
16
#11500
02
03
01
0;
0:
#11550
08
#11600
1,
1-
07
06
#11650
12
10
13
1;
1:
#11700
19
#11750
b10 A
b100 T
b1 W
b100 .
b100 R
b100 \
b10 *
b10 X
15
b11 N
0,
0-
17
16
#11800
02
00
03
0;
0:
#11850
09
#11900
1,
07
06
#11950
12
1;
#12050
b11 T
b11 .
b11 R
b11 \
b0 W
0,
17
#12100
02
0;
#12200
1,
07
#12250
12
1;
#12350
b10 B
14
b11 Y
0,
17
#12400
02
0;
#12500
07
#12900
b11 <
b11 >
b11 [
b11 ]
b0 =
#13000
b0 T
b1111 S
b0 I
b1111 H
b0 *
b0 X
b1000000000 .
b1000000000 R
b1000000000 \
b1011 W
1Q
04
b1 Y
b0 +
b0 M
b1000000000 /
b1000000000 G
b1000000000 Z
b1001 L
1F
05
b1 N
1@
#13100
1-
1,
0F
b10 N
0Q
b10 Y
0@
#13150
13
12
1:
1;
#13250
b10111 H
b10110 T
b11000 S
b100000000 /
b100000000 G
b100000000 Z
b1000 L
b11110110 .
b11110110 R
b11110110 \
b1010 W
0-
0,
16
17
#13300
03
02
0:
0;
#13400
1-
1,
06
07
#13450
13
12
1:
1;
#13550
b11011 H
b10001 T
b11100 S
b10000000 /
b10000000 G
b10000000 Z
b111 L
b1110001 .
b1110001 R
b1110001 \
b1001 W
0-
0,
16
17
#13600
03
02
0:
0;
#13700
1-
1,
06
07
#13750
13
12
1:
1;
#13850
b11101 H
b1 T
b11101 S
b1000000 /
b1000000 G
b1000000 Z
b110 L
b1000001 .
b1000001 R
b1000001 \
b1000 W
0-
0,
16
17
#13900
03
02
0:
0;
#14000
1-
1,
06
07
#14050
13
12
1:
1;
#14150
b11110 H
b101 T
b11110 S
b100000 /
b100000 G
b100000 Z
b101 L
b100101 .
b100101 R
b100101 \
b111 W
0-
0,
16
17
#14200
03
02
0:
0;
#14300
1-
1,
06
07
#14350
13
12
1:
1;
#14450
b10000 I
b11111 H
b10101 T
b11111 S
b10000 /
b10000 G
b10000 Z
b100 L
b10101 .
b10101 R
b10101 \
b110 W
0-
0,
16
17
#14500
03
02
0:
0;
#14600
1-
1,
06
07
#14650
13
12
1:
1;
#14750
b1000 I
b1101 T
b1000 /
b1000 G
b1000 Z
b11 L
b1101 .
b1101 R
b1101 \
b101 W
0-
0,
16
17
#14800
03
02
0:
0;
#14900
1-
1,
06
07
#14950
13
12
1:
1;
#15050
b100 I
b111 T
b100 /
b100 G
b100 Z
b10 L
b111 .
b111 R
b111 \
b100 W
0-
0,
16
17
#15100
03
02
0:
0;
#15200
1-
1,
06
07
#15250
13
12
1:
1;
#15350
b10 I
b100 T
b10 /
b10 G
b10 Z
b1 L
b100 .
b100 R
b100 \
b11 W
0-
0,
16
17
#15400
03
02
0:
0;
#15500
1-
1,
06
07
#15550
13
11
12
1:
1;
#15600
18
#15650
b11 I
b10 T
b0 L
b11 /
b11 G
b11 Z
b10 +
b10 M
b10 .
b10 R
b10 \
b10 W
0-
0,
16
17
#15700
03
01
02
0:
0;
#15750
08
#15800
1-
1,
06
07
#15850
13
11
12
10
1:
1;
#15900
18
19
#15950
b11 A
b100 I
b100 T
15
b11 N
b100 /
b100 G
b100 Z
b11 +
b11 M
b1 W
b100 .
b100 R
b100 \
b10 *
b10 X
0-
0,
16
17
#16000
03
01
02
00
0:
0;
#16050
08
09
#16100
1,
06
07
#16150
12
1;
#16250
b11 T
b11 .
b11 R
b11 \
b0 W
0,
17
#16300
02
0;
#16400
1,
07
#16450
12
10
1;
#16500
19
#16550
b11 B
b100 T
14
b11 Y
b100 .
b100 R
b100 \
b11 *
b11 X
0,
17
#16600
02
00
0;
#16650
09
#16700
07
#17100
b100 <
b100 >
b100 [
b100 ]
b0 =
#17200
b0 I
b1111 H
b0 T
b1111 S
b0 +
b0 M
b1000000000 /
b1000000000 G
b1000000000 Z
b1001 L
1F
05
b1 N
b0 *
b0 X
b1000000000 .
b1000000000 R
b1000000000 \
b1011 W
1Q
04
b1 Y
1@
#17300
1,
1-
0Q
b10 Y
0F
b10 N
0@
#17350
12
13
1;
1:
#17450
b10110 T
b11000 S
b10111 H
b11110110 .
b11110110 R
b11110110 \
b1010 W
b100000000 /
b100000000 G
b100000000 Z
b1000 L
0,
0-
17
16
#17500
02
03
0;
0:
#17600
1,
1-
07
06
#17650
12
13
1;
1:
#17750
b10001 T
b11100 S
b11011 H
b1110001 .
b1110001 R
b1110001 \
b1001 W
b10000000 /
b10000000 G
b10000000 Z
b111 L
0,
0-
17
16
#17800
02
03
0;
0:
#17900
1,
1-
07
06
#17950
12
13
1;
1:
#18050
b1 T
b11101 S
b11101 H
b1000001 .
b1000001 R
b1000001 \
b1000 W
b1000000 /
b1000000 G
b1000000 Z
b110 L
0,
0-
17
16
#18100
02
03
0;
0:
#18200
1,
1-
07
06
#18250
12
13
1;
1:
#18350
b101 T
b11110 S
b11110 H
b100101 .
b100101 R
b100101 \
b111 W
b100000 /
b100000 G
b100000 Z
b101 L
0,
0-
17
16
#18400
02
03
0;
0:
#18500
1,
1-
07
06
#18550
12
13
1;
1:
#18650
b10101 T
b11111 S
b10000 I
b11111 H
b10101 .
b10101 R
b10101 \
b110 W
b10000 /
b10000 G
b10000 Z
b100 L
0,
0-
17
16
#18700
02
03
0;
0:
#18800
1,
1-
07
06
#18850
12
13
1;
1:
#18950
b1101 T
b1000 I
b1101 .
b1101 R
b1101 \
b101 W
b1000 /
b1000 G
b1000 Z
b11 L
0,
0-
17
16
#19000
02
03
0;
0:
#19100
1,
1-
07
06
#19150
12
13
1;
1:
#19250
b111 T
b100 I
b111 .
b111 R
b111 \
b100 W
b100 /
b100 G
b100 Z
b10 L
0,
0-
17
16
#19300
02
03
0;
0:
#19400
1,
1-
07
06
#19450
12
13
11
1;
1:
#19500
18
#19550
b100 T
b110 I
b100 .
b100 R
b100 \
b11 W
b1 L
b110 /
b110 G
b110 Z
b100 +
b100 M
0,
0-
17
16
#19600
02
03
01
0;
0:
#19650
08
#19700
1,
1-
07
06
#19750
12
10
13
1;
1:
#19800
19
#19850
b110 T
b101 I
b10 W
b110 .
b110 R
b110 \
b100 *
b100 X
b101 /
b101 G
b101 Z
b0 L
0,
0-
17
16
#19900
02
00
03
0;
0:
#19950
09
#20000
1,
1-
07
06
#20050
12
13
1;
1:
#20150
b100 A
b1 W
15
b11 N
0,
0-
17
16
#20200
02
03
0;
0:
#20300
1,
07
06
#20350
12
1;
#20450
b101 T
b101 .
b101 R
b101 \
b0 W
0,
17
#20500
02
0;
#20600
1,
07
#20650
12
1;
#20750
b100 B
14
b11 Y
0,
17
#20800
02
0;
#20900
07
#21300
b101 <
b101 >
b101 [
b101 ]
b0 =
#21400
b0 T
b1111 S
b0 I
b1111 H
b0 *
b0 X
b1000000000 .
b1000000000 R
b1000000000 \
b1011 W
1Q
04
b1 Y
b0 +
b0 M
b1000000000 /
b1000000000 G
b1000000000 Z
b1001 L
1F
05
b1 N
1@
#21500
1-
1,
0F
b10 N
0Q
b10 Y
0@
#21550
13
12
1:
1;
#21650
b10111 H
b10110 T
b11000 S
b100000000 /
b100000000 G
b100000000 Z
b1000 L
b11110110 .
b11110110 R
b11110110 \
b1010 W
0-
0,
16
17
#21700
03
02
0:
0;
#21800
1-
1,
06
07
#21850
13
12
1:
1;
#21950
b11011 H
b10001 T
b11100 S
b10000000 /
b10000000 G
b10000000 Z
b111 L
b1110001 .
b1110001 R
b1110001 \
b1001 W
0-
0,
16
17
#22000
03
02
0:
0;
#22100
1-
1,
06
07
#22150
13
12
1:
1;
#22250
b11101 H
b1 T
b11101 S
b1000000 /
b1000000 G
b1000000 Z
b110 L
b1000001 .
b1000001 R
b1000001 \
b1000 W
0-
0,
16
17
#22300
03
02
0:
0;
#22400
1-
1,
06
07
#22450
13
12
1:
1;
#22550
b11110 H
b101 T
b11110 S
b100000 /
b100000 G
b100000 Z
b101 L
b100101 .
b100101 R
b100101 \
b111 W
0-
0,
16
17
#22600
03
02
0:
0;
#22700
1-
1,
06
07
#22750
13
12
1:
1;
#22850
b10000 I
b11111 H
b10101 T
b11111 S
b10000 /
b10000 G
b10000 Z
b100 L
b10101 .
b10101 R
b10101 \
b110 W
0-
0,
16
17
#22900
03
02
0:
0;
#23000
1-
1,
06
07
#23050
13
12
1:
1;
#23150
b1000 I
b1101 T
b1000 /
b1000 G
b1000 Z
b11 L
b1101 .
b1101 R
b1101 \
b101 W
0-
0,
16
17
#23200
03
02
0:
0;
#23300
1-
1,
06
07
#23350
13
12
1:
1;
#23450
b100 I
b111 T
b100 /
b100 G
b100 Z
b10 L
b111 .
b111 R
b111 \
b100 W
0-
0,
16
17
#23500
03
02
0:
0;
#23600
1-
1,
06
07
#23650
13
11
12
1:
1;
#23700
18
