adc_hdl/adc_fsm_10b_real/ideal_comparator_10b.v
module ideal_comparator_10b(  vip, 
                              vin, 
                              comp_result, 
                              comp_done, 
                              clk, 
                              rst);
   
   input [9:0] vip, vin;
   input clk, rst;
   output reg comp_result, comp_done;

   always @ (posedge clk) begin
      if (!comp_done) begin
         comp_result <= (vip >= vin);
         comp_done <= 1;
      end
   end
   
   always @ (negedge clk or rst) begin
      comp_result <= 0;
      comp_done <= 0;
   end
   
endmodule

adc_hdl/adc_fsm_10b_real/adc_fsm_10b_v1.v
// Adapted from http://math-crunching.blogspot.com/2015/12/sar-logic-verilog-hdl-code.html
// YYK: converted into sort of asynchronous circuit
// implemented as a state machine
// 30th december 2019

`timescale 100ns/1ns

module adc_fsm_10b_v1(  st_conv,
                        clkout,
                        clkin,
                        sample,
                        result,
                        dac_value,
                        dac_msb,
                        dac_lsb,
                        comp_in,
                        adc_done,
                        rst,
                        sel_12b,
                        cal);
                        
   input  st_conv;         // positive edge starts sampling, negative edge starts conversion
   output clkout;          // clock output to comparator
   input  clkin;           // clock input from comparator
   output sample;          // to S&H switch. Active high
   output [9:0] result;    // final result
   output [9:0] dac_value; // value to feed DAC
   output [9:5] dac_msb;   // value for DAC MSB array
   output [4:0] dac_lsb;   // value for DAC LSB array
   input comp_in;          // comparator result
   output adc_done;        // done=1 when conversion finishes
   input rst;              // for resetting the fsm
   input sel_12b;          // for selecting 12 steps or 10 steps. High means choose 12.
   input cal;              // for calibrating out ADC comparator offset
   
   reg [9:0] offset;          // For storing comparator offset
   wire clkout;               // clock output to comparator
   // Internal variables and registers
   reg [1:0] state;           // current state in state machine
   reg [9:0] result;         // final ADC answer
   reg [3:0] pointer;         // pointer for the search algo to index the steps
   reg [9:0] steps [11:0];   // array to store step sizes. 10-bit wide steps with depth of 12 steps
   reg [3:0] defaultpointer;  // default pointer to index the ADC steps
   
   // state assignment
   parameter sWait=0, sSample=1, sConv=2, sDone=3;   
   
   // Initialize the step sizes based on T.Ogawa's 2010 paper
   always @ (posedge rst) begin
      if (sel_12b==1) begin
         steps[11] <= 10'd512;
         steps[10] <= 10'd246;
         steps[9]  <= 10'd113;
         steps[8]  <= 10'd65;
         steps[7]  <= 10'd37;
         steps[6]  <= 10'd21;
         steps[5]  <= 10'd13;
         steps[4]  <= 10'd7;
         steps[3]  <= 10'd4;
         steps[2]  <= 10'd2;
         steps[1]  <= 10'd2;
         steps[0]  <= 10'd1;
         defaultpointer <= 4'd11;
      end
      else begin
         steps[11]<= 10'd512;
         steps[10]<= 10'd512;
         steps[9] <= 10'd512;
         steps[8] <= 10'd256;
         steps[7] <= 10'd128;
         steps[6] <= 10'd64;
         steps[5] <= 10'd32;
         steps[4] <= 10'd16;
         steps[3] <= 10'd8;
         steps[2] <= 10'd4;
         steps[1] <= 10'd2;
         steps[0] <= 10'd1;
         defaultpointer <= 4'd9;
      end
      state    <= sWait;
      result   <= 0;
      offset   <= 10'd0;
      pointer  <= 0;
   end
   
   always @ (posedge st_conv) begin
      // If st_conv goes high, start the sampling switch
      state    <= sSample;
      pointer  <= defaultpointer;
      if (cal)
         result   <= 10'b0;
      else
         result   <= 10'b0 - offset;
   end
   
   always @ (negedge st_conv) begin
      // If st_conv has a falling edge, start the conversion
      state    <= sConv;
   end
   
   // synchronous design
   always @(posedge clkin) begin
   case (state) // choose next state in state machine
      sConv :
         begin
            // clkout <= 0;
            if (comp_in) 
               result <= result + steps[pointer];
            
            // finished once LSB has been done
            if (pointer==0)  begin
               state    <= sDone;
               pointer  <= pointer;
               if (cal) begin
                  offset <= 10'd512 - (result + (steps[pointer] && comp_in));
               end
            end
            else begin
               state    <= sConv;
               pointer  <= pointer - 1;
            end
         end
      sDone :   state   <= sWait;
      default : state   <= sWait;
   endcase
   end
   
   assign clkout = (!clkin & (state==sConv));
   assign sample = (state==sSample);  // drive sample and hold
   assign dac_value = result + steps[pointer]; // to drive DAC
   assign dac_lsb[4:0] = dac_value[4:0];
   assign dac_msb[9:5] = 5'd31 - dac_value[9:5];
   assign adc_done = state==sDone;  // indicate when finished

endmodule

adc_hdl/adc_fsm_10b_real/testbench_adc_fsm_12s.v
`timescale 100ns/1ns

module testbench_adc_fsm_12s;
   
   wire fire_comp1, comp_done1, comp_result1, sample1, adc_done1;
   wire fire_comp2, comp_done2, comp_result2, sample2, adc_done2;
   wire [9:0] dac_value1, result1;
   wire [9:0] dac_value2, result2;
   reg  [9:0] reference = 0;
   
   reg delayed_comp_done1=0;
   reg delayed_comp_done2=0;
   reg delayed_comp_result1=0;
   reg delayed_comp_result2=0;
   reg delayed_fire_comp1=0;
   reg delayed_fire_comp2=0;
   reg st_conv, rst;
   
   reg [12:0] index = 0;      // Loop counter
   reg [12:0] innerindex = 0; // Inner loop counter
   reg [11:0] summary_results1;
   reg [11:0] summary_results2;
   
   integer textfile1 = 0;
   
   always @(comp_done1) delayed_comp_done1 <= #1 comp_done1;
   always @(comp_done2) delayed_comp_done2 <= #1 comp_done2;
   
   always @(comp_result1) delayed_comp_result1 <= #0.5 comp_result1;
   always @(comp_result2) delayed_comp_result2 <= #0.5 comp_result2;
   
   always @(fire_comp1) delayed_fire_comp1 <= #0.5 fire_comp1;
   always @(fire_comp2) delayed_fire_comp2 <= #0.5 fire_comp2;
   
   adc_fsm_10b_v1 adc1( .st_conv(st_conv),
                        .clkout(fire_comp1),
                        .clkin(delayed_comp_done1),
                        .sample(),
                        .result(result1),
                        .dac_value(dac_value1),
                        .dac_msb(),
                        .dac_lsb(),
                        .comp_in(delayed_comp_result1),
                        .adc_done(adc_done1),
                        .rst(rst),
                        .sel_12b(1'b0),
                        .cal(1'b0));

   ideal_comparator_10b comp1(.vip(reference), 
                              .vin(dac_value1), 
                              .comp_result(comp_result1), 
                              .comp_done(comp_done1), 
                              .clk(delayed_fire_comp1), 
                              .rst(rst));
   
   adc_fsm_10b_v1 adc2( .st_conv(st_conv),
                        .clkout(fire_comp2),
                        .clkin(delayed_comp_done2),
                        .sample(),
                        .result(result2),
                        .dac_value(dac_value2),
                        .dac_msb(),
                        .dac_lsb(),
                        .comp_in(delayed_comp_result2),
                        .adc_done(adc_done2),
                        .rst(rst),
                        .sel_12b(1'b1),
                        .cal(1'b0));
                           
   ideal_comparator_10b comp2(.vip(reference), 
                              .vin(dac_value2), 
                              .comp_result(comp_result2), 
                              .comp_done(comp_done2), 
                              .clk(delayed_fire_comp2), 
                              .rst(rst));
   
   always @ (posedge adc_done1 or posedge rst) begin
      if (rst) 
         summary_results1 <= 0;
      else
         summary_results1 <= result1;
   end
   
   always @ (posedge adc_done2 or posedge rst) begin
      if (rst) 
         summary_results2 <= 0;
      else
         summary_results2 <= result2;
   end
   
   initial begin
      st_conv = 0;
      rst = 0;
      textfile1 = $fopen("output1.csv","w");
      $fwrite(textfile1,"ref,adc1,adc2,\n");
      $dumpfile("log.vcd");
		$dumpvars;
      #1 rst = 0;
      #1 rst = 1;
      #1 rst = 0;
      
      for (index=0; index<1024; index = index + 1) begin
         for (innerindex=0;innerindex<1; innerindex = innerindex+1) begin
            #1 st_conv = 1;
            #1 st_conv = 0;
            #40 $fwrite(textfile1,"%d,%d,%d\n",reference,summary_results1,summary_results2);
         end
         reference = reference + 1;
      end
      
      #1 $fclose(textfile1);
      #10 $finish;
   end

endmodule

adc_hdl/adc_fsm_10b_real/log.vcd
$date
	Mon Dec 30 15:50:35 2019
$end
$version
	Icarus Verilog
$end
$timescale
	1ns
$end
$scope module testbench_adc_fsm_12s $end
$var wire 10 ! result2 [9:0] $end
$var wire 10 " result1 [9:0] $end
$var wire 1 # fire_comp2 $end
$var wire 1 $ fire_comp1 $end
$var wire 10 % dac_value2 [9:0] $end
$var wire 10 & dac_value1 [9:0] $end
$var wire 1 ' comp_result2 $end
$var wire 1 ( comp_result1 $end
$var wire 1 ) comp_done2 $end
$var wire 1 * comp_done1 $end
$var wire 1 + adc_done2 $end
$var wire 1 , adc_done1 $end
$var reg 1 - delayed_comp_done1 $end
$var reg 1 . delayed_comp_done2 $end
$var reg 1 / delayed_comp_result1 $end
$var reg 1 0 delayed_comp_result2 $end
$var reg 1 1 delayed_fire_comp1 $end
$var reg 1 2 delayed_fire_comp2 $end
$var reg 13 3 index [12:0] $end
$var reg 13 4 innerindex [12:0] $end
$var reg 10 5 reference [9:0] $end
$var reg 1 6 rst $end
$var reg 1 7 st_conv $end
$var reg 12 8 summary_results1 [11:0] $end
$var reg 12 9 summary_results2 [11:0] $end
$var integer 32 : textfile1 [31:0] $end
$scope module adc1 $end
$var wire 1 ; cal $end
$var wire 1 - clkin $end
$var wire 1 $ clkout $end
$var wire 1 / comp_in $end
$var wire 1 6 rst $end
$var wire 1 < sel_12b $end
$var wire 1 7 st_conv $end
$var wire 1 = sample $end
$var wire 10 > dac_value [9:0] $end
$var wire 5 ? dac_msb [9:5] $end
$var wire 5 @ dac_lsb [4:0] $end
$var wire 1 , adc_done $end
$var reg 4 A defaultpointer [3:0] $end
$var reg 10 B offset [9:0] $end
$var reg 4 C pointer [3:0] $end
$var reg 10 D result [9:0] $end
$var reg 2 E state [1:0] $end
$upscope $end
$scope module adc2 $end
$var wire 1 F cal $end
$var wire 1 . clkin $end
$var wire 1 # clkout $end
$var wire 1 0 comp_in $end
$var wire 1 6 rst $end
$var wire 1 G sel_12b $end
$var wire 1 7 st_conv $end
$var wire 1 H sample $end
$var wire 10 I dac_value [9:0] $end
$var wire 5 J dac_msb [9:5] $end
$var wire 5 K dac_lsb [4:0] $end
$var wire 1 + adc_done $end
$var reg 4 L defaultpointer [3:0] $end
$var reg 10 M offset [9:0] $end
$var reg 4 N pointer [3:0] $end
$var reg 10 O result [9:0] $end
$var reg 2 P state [1:0] $end
$upscope $end
$scope module comp1 $end
$var wire 1 1 clk $end
$var wire 1 6 rst $end
$var wire 10 Q vin [9:0] $end
$var wire 10 R vip [9:0] $end
$var reg 1 * comp_done $end
$var reg 1 ( comp_result $end
$upscope $end
$scope module comp2 $end
$var wire 1 2 clk $end
$var wire 1 6 rst $end
$var wire 10 S vin [9:0] $end
$var wire 10 T vip [9:0] $end
$var reg 1 ) comp_done $end
$var reg 1 ' comp_result $end
$upscope $end
$upscope $end
$enddefinitions $end
#0
$dumpvars
b0 T
bx S
b0 R
bx Q
b10 P
bx O
bx N
bx M
bx L
bx K
bx J
bx I
0H
1G
0F
b10 E
bx D
bx C
bx B
bx A
bx @
bx ?
bx >
0=
0<
0;
b10000000000000000000000000000011 :
bx 9
bx 8
07
06
b0 5
b0 4
b0 3
02
01
00
0/
0.
0-
0,
0+
0*
0)
0(
0'
bx &
bx %
1$
1#
bx "
bx !
$end
#50
1*
x(
1)
x'
11
12
#100
x/
x0
#150
0$
0#
1-
1.
#200
b1 @
b11111 ?
b1 K
b11111 J
b1 &
b1 >
b1 Q
b0 C
b0 B
b0 "
b0 D
b0 E
b1001 A
b1 %
b1 I
b1 S
b0 N
b0 M
b0 !
b0 O
b0 P
b1011 L
0*
0(
0)
0'
b0 8
b0 9
01
02
16
#250
0/
00
#300
0-
0.
06
#400
b0 @
b1111 ?
b0 K
b1111 J
b1000000000 &
b1000000000 >
b1000000000 Q
b1001 C
1=
b1 E
b1000000000 %
b1000000000 I
b1000000000 S
b1011 N
1H
b1 P
17
#500
1#
1$
0H
b10 P
0=
b10 E
07
#550
1)
1*
12
11
#650
b10110 K
b11000 J
b10111 ?
b11110110 %
b11110110 I
b11110110 S
b1010 N
b100000000 &
b100000000 >
b100000000 Q
b1000 C
0#
0$
1.
1-
#700
0)
0*
02
01
#800
1#
1$
0.
0-
#850
1)
1*
12
11
#950
b10001 K
b11100 J
b11011 ?
b1110001 %
b1110001 I
b1110001 S
b1001 N
b10000000 &
b10000000 >
b10000000 Q
b111 C
0#
0$
1.
1-
#1000
0)
0*
02
01
#1100
1#
1$
0.
0-
#1150
1)
1*
12
11
#1250
b1 K
b11101 J
b11101 ?
b1000001 %
b1000001 I
b1000001 S
b1000 N
b1000000 &
b1000000 >
b1000000 Q
b110 C
0#
0$
1.
1-
#1300
0)
0*
02
01
#1400
1#
1$
0.
0-
#1450
1)
1*
12
11
#1550
b101 K
b11110 J
b11110 ?
b100101 %
b100101 I
b100101 S
b111 N
b100000 &
b100000 >
b100000 Q
b101 C
0#
0$
1.
1-
#1600
0)
0*
02
01
#1700
1#
1$
0.
0-
#1750
1)
1*
12
11
#1850
b10101 K
b11111 J
b10000 @
b11111 ?
b10101 %
b10101 I
b10101 S
b110 N
b10000 &
b10000 >
b10000 Q
b100 C
0#
0$
1.
1-
#1900
0)
0*
02
01
#2000
1#
1$
0.
0-
#2050
1)
1*
12
11
#2150
b1101 K
b1000 @
b1101 %
b1101 I
b1101 S
b101 N
b1000 &
b1000 >
b1000 Q
b11 C
0#
0$
1.
1-
#2200
0)
0*
02
01
#2300
1#
1$
0.
0-
#2350
1)
1*
12
11
#2450
b111 K
b100 @
b111 %
b111 I
b111 S
b100 N
b100 &
b100 >
b100 Q
b10 C
0#
0$
1.
1-
#2500
0)
0*
02
01
#2600
1#
1$
0.
0-
#2650
1)
1*
12
11
#2750
b100 K
b10 @
b100 %
b100 I
b100 S
b11 N
b10 &
b10 >
b10 Q
b1 C
0#
0$
1.
1-
#2800
0)
0*
02
01
#2900
1#
1$
0.
0-
#2950
1)
1*
12
11
#3050
b10 K
b1 @
b10 %
b10 I
b10 S
b10 N
b1 &
b1 >
b1 Q
b0 C
0#
0$
1.
1-
#3100
0)
0*
02
01
#3200
1#
1$
0.
0-
#3250
1)
1*
12
11
#3350
b1 N
1,
b11 E
0#
0$
1.
1-
#3400
0)
0*
02
01
#3500
1#
0.
0-
#3550
1)
12
#3650
b1 K
b1 %
b1 I
b1 S
b0 N
0#
1.
#3700
0)
02
#3800
1#
0.
#3850
1)
12
#3950
1+
b11 P
0#
1.
#4000
0)
02
#4100
0.
#4500
b1 3
b1 5
b1 R
b1 T
b0 4
#4600
b0 K
b1111 J
b0 @
b1111 ?
b1000000000 %
b1000000000 I
b1000000000 S
b1011 N
1H
0+
b1 P
b1000000000 &
b1000000000 >
b1000000000 Q
b1001 C
1=
0,
b1 E
17
#4700
1$
1#
0=
b10 E
0H
b10 P
07
#4750
1*
1)
11
12
#4850
b10111 ?
b10110 K
b11000 J
b100000000 &
b100000000 >
b100000000 Q
b1000 C
b11110110 %
b11110110 I
b11110110 S
b1010 N
0$
0#
1-
1.
#4900
0*
0)
01
02
#5000
1$
1#
0-
0.
#5050
1*
1)
11
12
#5150
b11011 ?
b10001 K
b11100 J
b10000000 &
b10000000 >
b10000000 Q
b111 C
b1110001 %
b1110001 I
b1110001 S
b1001 N
0$
0#
1-
1.
#5200
0*
0)
01
02
#5300
1$
1#
0-
0.
#5350
1*
1)
11
12
#5450
b11101 ?
b1 K
b11101 J
b1000000 &
b1000000 >
b1000000 Q
b110 C
b1000001 %
b1000001 I
b1000001 S
b1000 N
0$
0#
1-
1.
#5500
0*
0)
01
02
#5600
1$
1#
0-
0.
#5650
1*
1)
11
12
#5750
b11110 ?
b101 K
b11110 J
b100000 &
b100000 >
b100000 Q
b101 C
b100101 %
b100101 I
b100101 S
b111 N
0$
0#
1-
1.
#5800
0*
0)
01
02
#5900
1$
1#
0-
0.
#5950
1*
1)
11
12
#6050
b10000 @
b11111 ?
b10101 K
b11111 J
b10000 &
b10000 >
b10000 Q
b100 C
b10101 %
b10101 I
b10101 S
b110 N
0$
0#
1-
1.
#6100
0*
0)
01
02
#6200
1$
1#
0-
0.
#6250
1*
1)
11
12
#6350
b1000 @
b1101 K
b1000 &
b1000 >
b1000 Q
b11 C
b1101 %
b1101 I
b1101 S
b101 N
0$
0#
1-
1.
#6400
0*
0)
01
02
#6500
1$
1#
0-
0.
#6550
1*
1)
11
12
#6650
b100 @
b111 K
b100 &
b100 >
b100 Q
b10 C
b111 %
b111 I
b111 S
b100 N
0$
0#
1-
1.
#6700
0*
0)
01
02
#6800
1$
1#
0-
0.
#6850
1*
1)
11
12
#6950
b10 @
b100 K
b10 &
b10 >
b10 Q
b1 C
b100 %
b100 I
b100 S
b11 N
0$
0#
1-
1.
#7000
0*
0)
01
02
#7100
1$
1#
0-
0.
#7150
1*
1)
11
12
#7250
b1 @
b10 K
b1 &
b1 >
b1 Q
b0 C
b10 %
b10 I
b10 S
b10 N
0$
0#
1-
1.
#7300
0*
0)
01
02
#7400
1$
1#
0-
0.
#7450
1*
1(
1)
11
12
#7500
1/
#7550
b1 8
b10 @
1,
b11 E
b10 &
b10 >
b10 Q
b1 "
b1 D
b1 N
0$
0#
1-
1.
#7600
0*
0(
0)
01
02
#7650
0/
#7700
1#
0-
0.
#7750
1)
12
#7850
b1 K
b1 %
b1 I
b1 S
b0 N
0#
1.
#7900
0)
02
#8000
1#
0.
#8050
1)
1'
12
#8100
10
#8150
b1 9
b10 K
1+
b11 P
b10 %
b10 I
b10 S
b1 !
b1 O
0#
1.
#8200
0)
0'
02
#8250
00
#8300
0.
#8700
b10 3
b10 5
b10 R
b10 T
b0 4
#8800
b0 @
b1111 ?
b0 K
b1111 J
b0 "
b0 D
b1000000000 &
b1000000000 >
b1000000000 Q
b1001 C
1=
0,
b1 E
b0 !
b0 O
b1000000000 %
b1000000000 I
b1000000000 S
b1011 N
1H
0+
b1 P
17
#8900
1#
1$
0H
b10 P
0=
b10 E
07
#8950
1)
1*
12
11
#9050
b10110 K
b11000 J
b10111 ?
b11110110 %
b11110110 I
b11110110 S
b1010 N
b100000000 &
b100000000 >
b100000000 Q
b1000 C
0#
0$
1.
1-
#9100
0)
0*
02
01
#9200
1#
1$
0.
0-
#9250
1)
1*
12
11
#9350
b10001 K
b11100 J
b11011 ?
b1110001 %
b1110001 I
b1110001 S
b1001 N
b10000000 &
b10000000 >
b10000000 Q
b111 C
0#
0$
1.
1-
#9400
0)
0*
02
01
#9500
1#
1$
0.
0-
#9550
1)
1*
12
11
#9650
b1 K
b11101 J
b11101 ?
b1000001 %
b1000001 I
b1000001 S
b1000 N
b1000000 &
b1000000 >
b1000000 Q
b110 C
0#
0$
1.
1-
#9700
0)
0*
02
01
#9800
1#
1$
0.
0-
#9850
1)
1*
12
11
#9950
b101 K
b11110 J
b11110 ?
b100101 %
b100101 I
b100101 S
b111 N
b100000 &
b100000 >
b100000 Q
b101 C
0#
0$
1.
1-
#10000
0)
0*
02
01
#10100
1#
1$
0.
0-
#10150
1)
1*
12
11
#10250
b10101 K
b11111 J
b10000 @
b11111 ?
b10101 %
b10101 I
b10101 S
b110 N
b10000 &
b10000 >
b10000 Q
b100 C
0#
0$
1.
1-
#10300
0)
0*
02
01
#10400
1#
1$
0.
0-
#10450
1)
1*
12
11
#10550
b1101 K
b1000 @
b1101 %
b1101 I
b1101 S
b101 N
b1000 &
b1000 >
b1000 Q
b11 C
0#
0$
1.
1-
#10600
0)
0*
02
01
#10700
1#
1$
0.
0-
#10750
1)
1*
12
11
#10850
b111 K
b100 @
b111 %
b111 I
b111 S
b100 N
b100 &
b100 >
b100 Q
b10 C
0#
0$
1.
1-
#10900
0)
0*
02
01
#11000
1#
1$
0.
0-
#11050
1)
1*
12
11
#11150
b100 K
b10 @
b100 %
b100 I
b100 S
b11 N
b10 &
b10 >
b10 Q
b1 C
0#
0$
1.
1-
#11200
0)
0*
02
01
#11300
1#
1$
0.
0-
#11350
1)
1*
1(
12
11
#11400
1/
#11450
b10 K
b11 @
b10 %
b10 I
b10 S
b10 N
b0 C
b11 &
b11 >
b11 Q
b10 "
b10 D
0#
0$
1.
1-
#11500
0)
0*
0(
02
01
#11550
0/
#11600
1#
1$
0.
0-
#11650
1)
1'
1*
12
11
#11700
10
#11750
b10 8
b100 K
b1 N
b100 %
b100 I
b100 S
b10 !
b10 O
1,
b11 E
0#
0$
1.
1-
#11800
0)
0'
0*
02
01
#11850
00
#11900
1#
0.
0-
#11950
1)
12
#12050
b11 K
b11 %
b11 I
b11 S
b0 N
0#
1.
#12100
0)
02
#12200
1#
0.
#12250
1)
12
#12350
b10 9
1+
b11 P
0#
1.
#12400
0)
02
#12500
0.
#12900
b11 3
b11 5
b11 R
b11 T
b0 4
#13000
b0 K
b1111 J
b0 @
b1111 ?
b0 !
b0 O
b1000000000 %
b1000000000 I
b1000000000 S
b1011 N
1H
0+
b1 P
b0 "
b0 D
b1000000000 &
b1000000000 >
b1000000000 Q
b1001 C
1=
0,
b1 E
17
#13100
1$
1#
0=
b10 E
0H
b10 P
07
#13150
1*
1)
11
12
#13250
b10111 ?
b10110 K
b11000 J
b100000000 &
b100000000 >
b100000000 Q
b1000 C
b11110110 %
b11110110 I
b11110110 S
b1010 N
0$
0#
1-
1.
#13300
0*
0)
01
02
#13400
1$
1#
0-
0.
#13450
1*
1)
11
12
#13550
b11011 ?
b10001 K
b11100 J
b10000000 &
b10000000 >
b10000000 Q
b111 C
b1110001 %
b1110001 I
b1110001 S
b1001 N
0$
0#
1-
1.
#13600
0*
0)
01
02
#13700
1$
1#
0-
0.
#13750
1*
1)
11
12
#13850
b11101 ?
b1 K
b11101 J
b1000000 &
b1000000 >
b1000000 Q
b110 C
b1000001 %
b1000001 I
b1000001 S
b1000 N
0$
0#
1-
1.
#13900
0*
0)
01
02
#14000
1$
1#
0-
0.
#14050
1*
1)
11
12
#14150
b11110 ?
b101 K
b11110 J
b100000 &
b100000 >
b100000 Q
b101 C
b100101 %
b100101 I
b100101 S
b111 N
0$
0#
1-
1.
#14200
0*
0)
01
02
#14300
1$
1#
0-
0.
#14350
1*
1)
11
12
#14450
b10000 @
b11111 ?
b10101 K
b11111 J
b10000 &
b10000 >
b10000 Q
b100 C
b10101 %
b10101 I
b10101 S
b110 N
0$
0#
1-
1.
#14500
0*
0)
01
02
#14600
1$
1#
0-
0.
#14650
1*
1)
11
12
#14750
b1000 @
b1101 K
b1000 &
b1000 >
b1000 Q
b11 C
b1101 %
b1101 I
b1101 S
b101 N
0$
0#
1-
1.
#14800
0*
0)
01
02
#14900
1$
1#
0-
0.
#14950
1*
1)
11
12
#15050
b100 @
b111 K
b100 &
b100 >
b100 Q
b10 C
b111 %
b111 I
b111 S
b100 N
0$
0#
1-
1.
#15100
0*
0)
01
02
#15200
1$
1#
0-
0.
#15250
1*
1)
11
12
#15350
b10 @
b100 K
b10 &
b10 >
b10 Q
b1 C
b100 %
b100 I
b100 S
b11 N
0$
0#
1-
1.
#15400
0*
0)
01
02
#15500
1$
1#
0-
0.
#15550
1*
1(
1)
11
12
#15600
1/
#15650
b11 @
b10 K
b0 C
b11 &
b11 >
b11 Q
b10 "
b10 D
b10 %
b10 I
b10 S
b10 N
0$
0#
1-
1.
#15700
0*
0(
0)
01
02
#15750
0/
#15800
1$
1#
0-
0.
#15850
1*
1(
1)
1'
11
12
#15900
1/
10
#15950
b11 8
b100 @
b100 K
1,
b11 E
b100 &
b100 >
b100 Q
b11 "
b11 D
b1 N
b100 %
b100 I
b100 S
b10 !
b10 O
0$
0#
1-
1.
#16000
0*
0(
0)
0'
01
02
#16050
0/
00
#16100
1#
0-
0.
#16150
1)
12
#16250
b11 K
b11 %
b11 I
b11 S
b0 N
0#
1.
#16300
0)
02
#16400
1#
0.
#16450
1)
1'
12
#16500
10
#16550
b11 9
b100 K
1+
b11 P
b100 %
b100 I
b100 S
b11 !
b11 O
0#
1.
#16600
0)
0'
02
#16650
00
#16700
0.
#17100
b100 3
b100 5
b100 R
b100 T
b0 4
#17200
b0 @
b1111 ?
b0 K
b1111 J
b0 "
b0 D
b1000000000 &
b1000000000 >
b1000000000 Q
b1001 C
1=
0,
b1 E
b0 !
b0 O
b1000000000 %
b1000000000 I
b1000000000 S
b1011 N
1H
0+
b1 P
17
#17300
1#
1$
0H
b10 P
0=
b10 E
07
#17350
1)
1*
12
11
#17450
b10110 K
b11000 J
b10111 ?
b11110110 %
b11110110 I
b11110110 S
b1010 N
b100000000 &
b100000000 >
b100000000 Q
b1000 C
0#
0$
1.
1-
#17500
0)
0*
02
01
#17600
1#
1$
0.
0-
#17650
1)
1*
12
11
#17750
b10001 K
b11100 J
b11011 ?
b1110001 %
b1110001 I
b1110001 S
b1001 N
b10000000 &
b10000000 >
b10000000 Q
b111 C
0#
0$
1.
1-
#17800
0)
0*
02
01
#17900
1#
1$
0.
0-
#17950
1)
1*
12
11
#18050
b1 K
b11101 J
b11101 ?
b1000001 %
b1000001 I
b1000001 S
b1000 N
b1000000 &
b1000000 >
b1000000 Q
b110 C
0#
0$
1.
1-
#18100
0)
0*
02
01
#18200
1#
1$
0.
0-
#18250
1)
1*
12
11
#18350
b101 K
b11110 J
b11110 ?
b100101 %
b100101 I
b100101 S
b111 N
b100000 &
b100000 >
b100000 Q
b101 C
0#
0$
1.
1-
#18400
0)
0*
02
01
#18500
1#
1$
0.
0-
#18550
1)
1*
12
11
#18650
b10101 K
b11111 J
b10000 @
b11111 ?
b10101 %
b10101 I
b10101 S
b110 N
b10000 &
b10000 >
b10000 Q
b100 C
0#
0$
1.
1-
#18700
0)
0*
02
01
#18800
1#
1$
0.
0-
#18850
1)
1*
12
11
#18950
b1101 K
b1000 @
b1101 %
b1101 I
b1101 S
b101 N
b1000 &
b1000 >
b1000 Q
b11 C
0#
0$
1.
1-
#19000
0)
0*
02
01
#19100
1#
1$
0.
0-
#19150
1)
1*
12
11
#19250
b111 K
b100 @
b111 %
b111 I
b111 S
b100 N
b100 &
b100 >
b100 Q
b10 C
0#
0$
1.
1-
#19300
0)
0*
02
01
#19400
1#
1$
0.
0-
#19450
1)
1*
1(
12
11
#19500
1/
#19550
b100 K
b110 @
b100 %
b100 I
b100 S
b11 N
b1 C
b110 &
b110 >
b110 Q
b100 "
b100 D
0#
0$
1.
1-
#19600
0)
0*
0(
02
01
#19650
0/
#19700
1#
1$
0.
0-
#19750
1)
1'
1*
12
11
#19800
10
#19850
b110 K
b101 @
b10 N
b110 %
b110 I
b110 S
b100 !
b100 O
b101 &
b101 >
b101 Q
b0 C
0#
0$
1.
1-
#19900
0)
0'
0*
02
01
#19950
00
#20000
1#
1$
0.
0-
#20050
1)
1*
12
11
#20150
b100 8
b1 N
1,
b11 E
0#
0$
1.
1-
#20200
0)
0*
02
01
#20300
1#
0.
0-
#20350
1)
12
#20450
b101 K
b101 %
b101 I
b101 S
b0 N
0#
1.
#20500
0)
02
#20600
1#
0.
#20650
1)
12
#20750
b100 9
1+
b11 P
0#
1.
#20800
0)
02
#20900
0.
#21300
b101 3
b101 5
b101 R
b101 T
b0 4
#21400
b0 K
b1111 J
b0 @
b1111 ?
b0 !
b0 O
b1000000000 %
b1000000000 I
b1000000000 S
b1011 N
1H
0+
b1 P
b0 "
b0 D
b1000000000 &
b1000000000 >
b1000000000 Q
b1001 C
1=
0,
b1 E
17
#21500
1$
1#
0=
b10 E
0H
b10 P
07
#21550
1*
1)
11
12
#21650
b10111 ?
b10110 K
b11000 J
b100000000 &
b100000000 >
b100000000 Q
b1000 C
b11110110 %
b11110110 I
b11110110 S
b1010 N
0$
0#
1-
1.
#21700
0*
0)
01
02
#21800
1$
1#
0-
0.
#21850
1*
1)
11
12
#21950
b11011 ?
b10001 K
b11100 J
b10000000 &
b10000000 >
b10000000 Q
b111 C
b1110001 %
b1110001 I
b1110001 S
b1001 N
0$
0#
1-
1.
#22000
0*
0)
01
02
#22100
1$
1#
0-
0.
#22150
1*
1)
11
12
#22250
b11101 ?
b1 K
b11101 J
b1000000 &
b1000000 >
b1000000 Q
b110 C
b1000001 %
b1000001 I
b1000001 S
b1000 N
0$
0#
1-
1.
#22300
0*
0)
01
02
#22400
1$
1#
0-
0.
#22450
1*
1)
11
12
#22550
b11110 ?
b101 K
b11110 J
b100000 &
b100000 >
b100000 Q
b101 C
b100101 %
b100101 I
b100101 S
b111 N
0$
0#
1-
1.
#22600
0*
0)
01
02
#22700
1$
1#
0-
0.
#22750
1*
1)
11
12
#22850
b10000 @
b11111 ?
b10101 K
b11111 J
b10000 &
b10000 >
b10000 Q
b100 C
b10101 %
b10101 I
b10101 S
b110 N
0$
0#
1-
1.
#22900
0*
0)
01
02
#23000
1$
1#
0-
0.
#23050
1*
1)
11
12
#23150
b1000 @
b1101 K
b1000 &
b1000 >
b1000 Q
b11 C
b1101 %
b1101 I
b1101 S
b101 N
0$
0#
1-
1.
#23200
0*
0)
01
02
#23300
1$
1#
0-
0.
#23350
1*
1)
11
12
#23450
b100 @
b111 K
b100 &
b100 >
b100 Q
b10 C
b111 %
b111 I
b111 S
b100 N
0$
0#
1-
1.
#23500
0*
0)
01
02
#23600
1$
1#
0-
0.
#23650
1*
1(
1)
11
12
#23700
1/
#23750
b110 @
b100 K
b1 C
b110 &
b110 >
b110 Q
b100 "
b100 D
b100 %
b100 I
b100 S
b11 N
0$
0#
1-
1.
#23800
0*
0(
0)
01
02
#23850
0/
#23900
1$
1#
0-
0.
#23950
1*
1)
1'
11
12
#24000
10
#24050
b101 @
b110 K
b101 &
b101 >
b101 Q
b0 C
b10 N
b110 %
b110 I
b110 S
b100 !
b100 O
0$
0#
1-
1.
#24100
0*
0)
0'
01
02
#24150
00
#24200
1$
1#
0-
0.
#24250
1*
1(
1)
11
12
#24300
1/
#24350
b101 8
b110 @
1,
b11 E
b110 &
b110 >
b110 Q
b101 "
b101 D
b1 N
0$
0#
1-
1.
#24400
0*
0(
0)
01
02
#24450
0/
#24500
1#
0-
0.
#24550
1)
12
#24650
b101 K
b101 %
b101 I
b101 S
b0 N
0#
1.
#24700
0)
02
#24800
1#
0.
#24850
1)
1'
12
#24900
10
#24950
b101 9
b110 K
1+
b11 P
b110 %
b110 I
b110 S
b101 !
b101 O
0#
1.
#25000
0)
0'
02
#25050
00
#25100
0.
#25500
b110 3
b110 5
b110 R
b110 T
b0 4
