adc_hdl/adc_fsm_10b_real/ideal_comparator_10b.v
module ideal_comparator_10b(  vip, 
                              vin, 
                              comp_result, 
                              comp_done, 
                              clk, 
                              rst);
   
   input [9:0] vip, vin;
   input clk, rst;
   output reg comp_result, comp_done;

   always @ (posedge clk) begin
      if (!comp_done) begin
         comp_result <= (vip >= vin);
         comp_done <= 1;
      end
   end
   
   always @ (negedge clk or rst) begin
      comp_result <= 0;
      comp_done <= 0;
   end
   
endmodule

adc_hdl/adc_fsm_10b_real/adc_fsm_10b_v1.v
// Adapted from http://math-crunching.blogspot.com/2015/12/sar-logic-verilog-hdl-code.html
// YYK: converted into sort of asynchronous circuit
// implemented as a state machine
// 30th december 2019

`timescale 100ns/1ns

module adc_fsm_10b_v1(  st_conv,
                        clkout,
                        clkin,
                        sample,
                        result,
                        dac_value,
                        dac_msb,
                        dac_lsb,
                        comp_in,
                        adc_done,
                        rst,
                        sel_12b,
                        cal);
                        
   input  st_conv;         // positive edge starts sampling, negative edge starts conversion
   output clkout;          // clock output to comparator
   input  clkin;           // clock input from comparator
   output sample;          // to S&H switch. Active high
   output [9:0] result;    // final result
   output [9:0] dac_value; // value to feed DAC
   output [9:5] dac_msb;   // value for DAC MSB array
   output [4:0] dac_lsb;   // value for DAC LSB array
   input comp_in;          // comparator result
   output adc_done;        // done=1 when conversion finishes
   input rst;              // for resetting the fsm
   input sel_12b;          // for selecting 12 steps or 10 steps. High means choose 12.
   input cal;              // for calibrating out ADC comparator offset
   
   reg [9:0] offset;          // For storing comparator offset
   wire clkout;               // clock output to comparator
   // Internal variables and registers
   reg [1:0] state;           // current state in state machine
   reg [9:0] result;         // final ADC answer
   reg [3:0] pointer;         // pointer for the search algo to index the steps
   reg [9:0] steps [11:0];   // array to store step sizes. 10-bit wide steps with depth of 12 steps
   reg [3:0] defaultpointer;  // default pointer to index the ADC steps
   
   // state assignment
   parameter sWait=0, sSample=1, sConv=2, sDone=3;   
   
   // Initialize the step sizes based on T.Ogawa's 2010 paper
   always @ (posedge rst) begin
      if (sel_12b==1) begin
         steps[11] <= 10'd512;
         steps[10] <= 10'd246;
         steps[9]  <= 10'd113;
         steps[8]  <= 10'd65;
         steps[7]  <= 10'd37;
         steps[6]  <= 10'd21;
         steps[5]  <= 10'd13;
         steps[4]  <= 10'd7;
         steps[3]  <= 10'd4;
         steps[2]  <= 10'd2;
         steps[1]  <= 10'd2;
         steps[0]  <= 10'd1;
         defaultpointer <= 4'd11;
      end
      else begin
         steps[11]<= 10'd512;
         steps[10]<= 10'd512;
         steps[9] <= 10'd512;
         steps[8] <= 10'd256;
         steps[7] <= 10'd128;
         steps[6] <= 10'd64;
         steps[5] <= 10'd32;
         steps[4] <= 10'd16;
         steps[3] <= 10'd8;
         steps[2] <= 10'd4;
         steps[1] <= 10'd2;
         steps[0] <= 10'd1;
         defaultpointer <= 4'd9;
      end
      state    <= sWait;
      result   <= 0;
      offset   <= 10'd0;
      pointer  <= 0;
   end
   
   always @ (posedge st_conv) begin
      // If st_conv goes high, start the sampling switch
      state    <= sSample;
      pointer  <= defaultpointer;
      if (cal)
         result   <= 10'b0;
      else
         result   <= 10'b0 - offset;
   end
   
   always @ (negedge st_conv) begin
      // If st_conv has a falling edge, start the conversion
      state    <= sConv;
   end
   
   // synchronous design
   always @(posedge clkin) begin
   case (state) // choose next state in state machine
      sConv :
         begin
            // clkout <= 0;
            if (comp_in) 
               result <= result + steps[pointer];
            
            // finished once LSB has been done
            if (pointer==0)  begin
               state    <= sDone;
               pointer  <= pointer;
               if (cal) begin
                  offset <= 10'd512 - (result + (steps[pointer] && comp_in));
               end
            end
            else begin
               state    <= sConv;
               pointer  <= pointer - 1;
            end
         end
      sDone :   state   <= sWait;
      default : state   <= sWait;
   endcase
   end
   
   assign clkout = (!clkin & (state==sConv));
   assign sample = (state==sSample);  // drive sample and hold
   assign dac_value = result + steps[pointer]; // to drive DAC
   assign dac_lsb[4:0] = dac_value[4:0];
   assign dac_msb[9:5] = 5'd31 - dac_value[9:5];
   assign adc_done = state==sDone;  // indicate when finished

endmodule

adc_hdl/adc_fsm_10b_real/testbench_adc_fsm_osc.v
`timescale 100ns/1ns

module testbench_adc_fsm_osc;
   
   wire fire_comp1, comp_done1, comp_result1, sample1, adc_done1;
   wire fire_comp2, comp_done2, comp_result2, sample2, adc_done2;
   wire [9:0] dac_value1, result1;
   wire [9:0] dac_value2, result2;
   reg  [9:0] reference = 0;
   
   reg delayed_comp_done1=0;
   reg delayed_comp_done2=0;
   reg delayed_comp_result1=0;
   reg delayed_comp_result2=0;
   reg delayed_fire_comp1=0;
   reg delayed_fire_comp2=0;
   reg st_conv, rst, cal;
   
   reg [9:0] offset = 100;      // Offset to model comparator offset
   reg [12:0] index = 0;      // Loop counter
   reg [12:0] innerindex = 0; // Inner loop counter
   reg [11:0] summary_results1;
   reg [11:0] summary_results2;
   
   integer textfile1 = 0;
   
   always @(comp_done1) delayed_comp_done1 <= #1 comp_done1;
   always @(comp_done2) delayed_comp_done2 <= #1 comp_done2;
   
   always @(comp_result1) delayed_comp_result1 <= #0.5 comp_result1;
   always @(comp_result2) delayed_comp_result2 <= #0.5 comp_result2;
   
   always @(fire_comp1) delayed_fire_comp1 <= #0.5 fire_comp1;
   always @(fire_comp2) delayed_fire_comp2 <= #0.5 fire_comp2;
   
   adc_fsm_10b_v1 adc1( .st_conv(st_conv),
                        .clkout(fire_comp1),
                        .clkin(delayed_comp_done1),
                        .sample(),
                        .result(result1),
                        .dac_value(dac_value1),
                        .dac_msb(),
                        .dac_lsb(),
                        .comp_in(delayed_comp_result1),
                        .adc_done(adc_done1),
                        .rst(rst),
                        .sel_12b(1'b1),
                        .cal(1'b0));

   ideal_comparator_10b comp1(.vip(reference), 
                              .vin(dac_value1+offset), 
                              .comp_result(comp_result1), 
                              .comp_done(comp_done1), 
                              .clk(delayed_fire_comp1), 
                              .rst(rst));
   
   adc_fsm_10b_v1 adc2( .st_conv(st_conv),
                        .clkout(fire_comp2),
                        .clkin(delayed_comp_done2),
                        .sample(),
                        .result(result2),
                        .dac_value(dac_value2),
                        .dac_msb(),
                        .dac_lsb(),
                        .comp_in(delayed_comp_result2),
                        .adc_done(adc_done2),
                        .rst(rst),
                        .sel_12b(1'b1),
                        .cal(cal));
                           
   ideal_comparator_10b comp2(.vip(reference), 
                              .vin(dac_value2+offset), 
                              .comp_result(comp_result2), 
                              .comp_done(comp_done2), 
                              .clk(delayed_fire_comp2), 
                              .rst(rst));
   
   always @ (posedge adc_done1 or posedge rst) begin
      if (rst) 
         summary_results1 <= 0;
      else
         summary_results1 <= result1;
   end
   
   always @ (posedge adc_done2 or posedge rst) begin
      if (rst) 
         summary_results2 <= 0;
      else
         summary_results2 <= result2;
   end
   
   initial begin
      st_conv = 0;
      rst = 0;
      cal = 0;
      textfile1 = $fopen("output_osc.csv","w");
      $fwrite(textfile1,"ref,adc1,adc2,\n");
      $dumpfile("log_osc.vcd");
		$dumpvars;
      #1 rst = 0;
      #1 rst = 1;
      #1 rst = 0;
      reference = 512;
      #1 cal = 1;
      #1 st_conv = 1;
      #1 st_conv = 0;
      #40 $fwrite(textfile1,"%d,%d,%d\n",reference,summary_results1,summary_results2);
      #1 cal = 0;
      
      for (index=0; index<1024; index = index + 1) begin
         for (innerindex=0;innerindex<1; innerindex = innerindex+1) begin
            #1 st_conv = 1;
            #1 st_conv = 0;
            #40 $fwrite(textfile1,"%d,%d,%d\n",reference,summary_results1,summary_results2);
         end
         reference = reference + 1;
      end
      
      #1 $fclose(textfile1);
      #10 $finish;
   end

endmodule

adc_hdl/adc_fsm_10b_real/log_osc.vcd
$date
	Mon Dec 30 15:44:09 2019
$end
$version
	Icarus Verilog
$end
$timescale
	1ns
$end
$scope module testbench_adc_fsm_osc $end
$var wire 10 ! result2 [9:0] $end
$var wire 10 " result1 [9:0] $end
$var wire 1 # fire_comp2 $end
$var wire 1 $ fire_comp1 $end
$var wire 10 % dac_value2 [9:0] $end
$var wire 10 & dac_value1 [9:0] $end
$var wire 1 ' comp_result2 $end
$var wire 1 ( comp_result1 $end
$var wire 1 ) comp_done2 $end
$var wire 1 * comp_done1 $end
$var wire 1 + adc_done2 $end
$var wire 1 , adc_done1 $end
$var reg 1 - cal $end
$var reg 1 . delayed_comp_done1 $end
$var reg 1 / delayed_comp_done2 $end
$var reg 1 0 delayed_comp_result1 $end
$var reg 1 1 delayed_comp_result2 $end
$var reg 1 2 delayed_fire_comp1 $end
$var reg 1 3 delayed_fire_comp2 $end
$var reg 13 4 index [12:0] $end
$var reg 13 5 innerindex [12:0] $end
$var reg 10 6 offset [9:0] $end
$var reg 10 7 reference [9:0] $end
$var reg 1 8 rst $end
$var reg 1 9 st_conv $end
$var reg 12 : summary_results1 [11:0] $end
$var reg 12 ; summary_results2 [11:0] $end
$var integer 32 < textfile1 [31:0] $end
$scope module adc1 $end
$var wire 1 = cal $end
$var wire 1 . clkin $end
$var wire 1 $ clkout $end
$var wire 1 0 comp_in $end
$var wire 1 8 rst $end
$var wire 1 > sel_12b $end
$var wire 1 9 st_conv $end
$var wire 1 ? sample $end
$var wire 10 @ dac_value [9:0] $end
$var wire 5 A dac_msb [9:5] $end
$var wire 5 B dac_lsb [4:0] $end
$var wire 1 , adc_done $end
$var reg 4 C defaultpointer [3:0] $end
$var reg 10 D offset [9:0] $end
$var reg 4 E pointer [3:0] $end
$var reg 10 F result [9:0] $end
$var reg 2 G state [1:0] $end
$upscope $end
$scope module adc2 $end
$var wire 1 - cal $end
$var wire 1 / clkin $end
$var wire 1 # clkout $end
$var wire 1 1 comp_in $end
$var wire 1 8 rst $end
$var wire 1 H sel_12b $end
$var wire 1 9 st_conv $end
$var wire 1 I sample $end
$var wire 10 J dac_value [9:0] $end
$var wire 5 K dac_msb [9:5] $end
$var wire 5 L dac_lsb [4:0] $end
$var wire 1 + adc_done $end
$var reg 4 M defaultpointer [3:0] $end
$var reg 10 N offset [9:0] $end
$var reg 4 O pointer [3:0] $end
$var reg 10 P result [9:0] $end
$var reg 2 Q state [1:0] $end
$upscope $end
$scope module comp1 $end
$var wire 1 2 clk $end
$var wire 1 8 rst $end
$var wire 10 R vin [9:0] $end
$var wire 10 S vip [9:0] $end
$var reg 1 * comp_done $end
$var reg 1 ( comp_result $end
$upscope $end
$scope module comp2 $end
$var wire 1 3 clk $end
$var wire 1 8 rst $end
$var wire 10 T vin [9:0] $end
$var wire 10 U vip [9:0] $end
$var reg 1 ) comp_done $end
$var reg 1 ' comp_result $end
$upscope $end
$upscope $end
$enddefinitions $end
#0
$dumpvars
b0 U
bx T
b0 S
bx R
b10 Q
bx P
bx O
bx N
bx M
bx L
bx K
bx J
0I
1H
b10 G
bx F
bx E
bx D
bx C
bx B
bx A
bx @
0?
1>
0=
b10000000000000000000000000000011 <
bx ;
bx :
09
08
b0 7
b1100100 6
b0 5
b0 4
03
02
01
00
0/
0.
0-
0,
0+
0*
0)
0(
0'
bx &
bx %
1$
1#
bx "
bx !
$end
#50
1*
x(
1)
x'
12
13
#100
x0
x1
#150
0$
0#
1.
1/
#200
b1 B
b11111 A
b1 L
b11111 K
b1100101 R
b1 &
b1 @
b0 E
b0 D
b0 "
b0 F
b0 G
b1011 C
b1100101 T
b1 %
b1 J
b0 O
b0 N
b0 !
b0 P
b0 Q
b1011 M
0*
0(
0)
0'
b0 :
b0 ;
02
03
18
#250
00
01
#300
0.
0/
08
#400
1-
#500
b0 B
b1111 A
b0 L
b1111 K
b1001100100 R
b1000000000 &
b1000000000 @
b1011 E
1?
b1 G
b1001100100 T
b1000000000 %
b1000000000 J
b1011 O
1I
b1 Q
19
#600
1#
1$
0I
b10 Q
0?
b10 G
09
#650
1)
1*
13
12
#750
b10110 L
b11000 K
b10110 B
b11000 A
b101011010 T
b11110110 %
b11110110 J
b1010 O
b101011010 R
b11110110 &
b11110110 @
b1010 E
0#
0$
1/
1.
#800
0)
0*
03
02
#900
1#
1$
0/
0.
#950
1)
1*
13
12
#1050
b10001 L
b11100 K
b10001 B
b11100 A
b11010101 T
b1110001 %
b1110001 J
b1001 O
b11010101 R
b1110001 &
b1110001 @
b1001 E
0#
0$
1/
1.
#1100
0)
0*
03
02
#1200
1#
1$
0/
0.
#1250
1)
1*
13
12
#1350
b1 L
b11101 K
b1 B
b11101 A
b10100101 T
b1000001 %
b1000001 J
b1000 O
b10100101 R
b1000001 &
b1000001 @
b1000 E
0#
0$
1/
1.
#1400
0)
0*
03
02
#1500
1#
1$
0/
0.
#1550
1)
1*
13
12
#1650
b101 L
b11110 K
b101 B
b11110 A
b10001001 T
b100101 %
b100101 J
b111 O
b10001001 R
b100101 &
b100101 @
b111 E
0#
0$
1/
1.
#1700
0)
0*
03
02
#1800
1#
1$
0/
0.
#1850
1)
1*
13
12
#1950
b10101 L
b11111 K
b10101 B
b11111 A
b1111001 T
b10101 %
b10101 J
b110 O
b1111001 R
b10101 &
b10101 @
b110 E
0#
0$
1/
1.
#2000
0)
0*
03
02
#2100
1#
1$
0/
0.
#2150
1)
1*
13
12
#2250
b1101 L
b1101 B
b1110001 T
b1101 %
b1101 J
b101 O
b1110001 R
b1101 &
b1101 @
b101 E
0#
0$
1/
1.
#2300
0)
0*
03
02
#2400
1#
1$
0/
0.
#2450
1)
1*
13
12
#2550
b111 L
b111 B
b1101011 T
b111 %
b111 J
b100 O
b1101011 R
b111 &
b111 @
b100 E
0#
0$
1/
1.
#2600
0)
0*
03
02
#2700
1#
1$
0/
0.
#2750
1)
1*
13
12
#2850
b100 L
b100 B
b1101000 T
b100 %
b100 J
b11 O
b1101000 R
b100 &
b100 @
b11 E
0#
0$
1/
1.
#2900
0)
0*
03
02
#3000
1#
1$
0/
0.
#3050
1)
1*
13
12
#3150
b10 L
b10 B
b1100110 T
b10 %
b10 J
b10 O
b1100110 R
b10 &
b10 @
b10 E
0#
0$
1/
1.
#3200
0)
0*
03
02
#3300
1#
1$
0/
0.
#3350
1)
1*
13
12
#3450
b1 O
b1 E
0#
0$
1/
1.
#3500
0)
0*
03
02
#3600
1#
1$
0/
0.
#3650
1)
1*
13
12
#3750
b1 L
b1 B
b1100101 T
b1 %
b1 J
b0 O
b1100101 R
b1 &
b1 @
b0 E
0#
0$
1/
1.
#3800
0)
0*
03
02
#3900
1#
1$
0/
0.
#3950
1)
1*
13
12
#4050
b1000000000 N
1+
b11 Q
1,
b11 G
0#
0$
1/
1.
#4100
0)
0*
03
02
#4200
0/
0.
#4700
0-
#4800
b0 L
b0 B
b1111 A
b1000000000 !
b1000000000 P
b1100100 T
b0 %
b0 J
b1011 O
1I
0+
b1 Q
b1001100100 R
b1000000000 &
b1000000000 @
b1011 E
1?
0,
b1 G
19
#4900
1$
1#
0?
b10 G
0I
b10 Q
09
#4950
1*
1)
12
13
#5050
b10110 B
b11000 A
b10110 L
b1000 K
b101011010 R
b11110110 &
b11110110 @
b1010 E
b1101011010 T
b1011110110 %
b1011110110 J
b1010 O
0$
0#
1.
1/
#5100
0*
0)
02
03
#5200
1$
1#
0.
0/
#5250
1*
1)
12
13
#5350
b10001 B
b11100 A
b10001 L
b1100 K
b11010101 R
b1110001 &
b1110001 @
b1001 E
b1011010101 T
b1001110001 %
b1001110001 J
b1001 O
0$
0#
1.
1/
#5400
0*
0)
02
03
#5500
1$
1#
0.
0/
#5550
1*
1)
12
13
#5650
b1 B
b11101 A
b1 L
b1101 K
b10100101 R
b1000001 &
b1000001 @
b1000 E
b1010100101 T
b1001000001 %
b1001000001 J
b1000 O
0$
0#
1.
1/
#5700
0*
0)
02
03
#5800
1$
1#
0.
0/
#5850
1*
1)
12
13
#5950
b101 B
b11110 A
b101 L
b1110 K
b10001001 R
b100101 &
b100101 @
b111 E
b1010001001 T
b1000100101 %
b1000100101 J
b111 O
0$
0#
1.
1/
#6000
0*
0)
02
03
#6100
1$
1#
0.
0/
#6150
1*
1)
12
13
#6250
b10101 B
b11111 A
b10101 L
b1111 K
b1111001 R
b10101 &
b10101 @
b110 E
b1001111001 T
b1000010101 %
b1000010101 J
b110 O
0$
0#
1.
1/
#6300
0*
0)
02
03
#6400
1$
1#
0.
0/
#6450
1*
1)
12
13
#6550
b1101 B
b1101 L
b1110001 R
b1101 &
b1101 @
b101 E
b1001110001 T
b1000001101 %
b1000001101 J
b101 O
0$
0#
1.
1/
#6600
0*
0)
02
03
#6700
1$
1#
0.
0/
#6750
1*
1)
12
13
#6850
b111 B
b111 L
b1101011 R
b111 &
b111 @
b100 E
b1001101011 T
b1000000111 %
b1000000111 J
b100 O
0$
0#
1.
1/
#6900
0*
0)
02
03
#7000
1$
1#
0.
0/
#7050
1*
1)
12
13
#7150
b100 B
b100 L
b1101000 R
b100 &
b100 @
b11 E
b1001101000 T
b1000000100 %
b1000000100 J
b11 O
0$
0#
1.
1/
#7200
0*
0)
02
03
#7300
1$
1#
0.
0/
#7350
1*
1)
12
13
#7450
b10 B
b10 L
b1100110 R
b10 &
b10 @
b10 E
b1001100110 T
b1000000010 %
b1000000010 J
b10 O
0$
0#
1.
1/
#7500
0*
0)
02
03
#7600
1$
1#
0.
0/
#7650
1*
1)
12
13
#7750
b1 E
b1 O
0$
0#
1.
1/
#7800
0*
0)
02
03
#7900
1$
1#
0.
0/
#7950
1*
1)
12
13
#8050
b1 B
b1 L
b1100101 R
b1 &
b1 @
b0 E
b1001100101 T
b1000000001 %
b1000000001 J
b0 O
0$
0#
1.
1/
#8100
0*
0)
02
03
#8200
1$
1#
0.
0/
#8250
1*
1)
12
13
#8350
b1000000000 ;
1,
b11 G
1+
b11 Q
0$
0#
1.
1/
#8400
0*
0)
02
03
#8500
0.
0/
#8900
b1 4
b1 7
b1 S
b1 U
b0 5
#9000
b0 B
b1111 A
b0 L
b11111 K
b1001100100 R
b1000000000 &
b1000000000 @
b1011 E
1?
0,
b1 G
b1100100 T
b0 %
b0 J
b1011 O
1I
0+
b1 Q
19
#9100
1#
1$
0I
b10 Q
0?
b10 G
09
#9150
1)
1*
13
12
#9250
b10110 L
b1000 K
b10110 B
b11000 A
b1101011010 T
b1011110110 %
b1011110110 J
b1010 O
b101011010 R
b11110110 &
b11110110 @
b1010 E
0#
0$
1/
1.
#9300
0)
0*
03
02
#9400
1#
1$
0/
0.
#9450
1)
1*
13
12
#9550
b10001 L
b1100 K
b10001 B
b11100 A
b1011010101 T
b1001110001 %
b1001110001 J
b1001 O
b11010101 R
b1110001 &
b1110001 @
b1001 E
0#
0$
1/
1.
#9600
0)
0*
03
02
#9700
1#
1$
0/
0.
#9750
1)
1*
13
12
#9850
b1 L
b1101 K
b1 B
b11101 A
b1010100101 T
b1001000001 %
b1001000001 J
b1000 O
b10100101 R
b1000001 &
b1000001 @
b1000 E
0#
0$
1/
1.
#9900
0)
0*
03
02
#10000
1#
1$
0/
0.
#10050
1)
1*
13
12
#10150
b101 L
b1110 K
b101 B
b11110 A
b1010001001 T
b1000100101 %
b1000100101 J
b111 O
b10001001 R
b100101 &
b100101 @
b111 E
0#
0$
1/
1.
#10200
0)
0*
03
02
#10300
1#
1$
0/
0.
#10350
1)
1*
13
12
#10450
b10101 L
b1111 K
b10101 B
b11111 A
b1001111001 T
b1000010101 %
b1000010101 J
b110 O
b1111001 R
b10101 &
b10101 @
b110 E
0#
0$
1/
1.
#10500
0)
0*
03
02
#10600
1#
1$
0/
0.
#10650
1)
1*
13
12
#10750
b1101 L
b1101 B
b1001110001 T
b1000001101 %
b1000001101 J
b101 O
b1110001 R
b1101 &
b1101 @
b101 E
0#
0$
1/
1.
#10800
0)
0*
03
02
#10900
1#
1$
0/
0.
#10950
1)
1*
13
12
#11050
b111 L
b111 B
b1001101011 T
b1000000111 %
b1000000111 J
b100 O
b1101011 R
b111 &
b111 @
b100 E
0#
0$
1/
1.
#11100
0)
0*
03
02
#11200
1#
1$
0/
0.
#11250
1)
1*
13
12
#11350
b100 L
b100 B
b1001101000 T
b1000000100 %
b1000000100 J
b11 O
b1101000 R
b100 &
b100 @
b11 E
0#
0$
1/
1.
#11400
0)
0*
03
02
#11500
1#
1$
0/
0.
#11550
1)
1*
13
12
#11650
b10 L
b10 B
b1001100110 T
b1000000010 %
b1000000010 J
b10 O
b1100110 R
b10 &
b10 @
b10 E
0#
0$
1/
1.
#11700
0)
0*
03
02
#11800
1#
1$
0/
0.
#11850
1)
1*
13
12
#11950
b1 O
b1 E
0#
0$
1/
1.
#12000
0)
0*
03
02
#12100
1#
1$
0/
0.
#12150
1)
1*
13
12
#12250
b1 L
b1 B
b1001100101 T
b1000000001 %
b1000000001 J
b0 O
b1100101 R
b1 &
b1 @
b0 E
0#
0$
1/
1.
#12300
0)
0*
03
02
#12400
1#
1$
0/
0.
#12450
1)
1*
13
12
#12550
1+
b11 Q
1,
b11 G
0#
0$
1/
1.
#12600
0)
0*
03
02
#12700
0/
0.
#13100
b10 4
b10 7
b10 S
b10 U
b0 5
#13200
b0 L
b11111 K
b0 B
b1111 A
b1100100 T
b0 %
b0 J
b1011 O
1I
0+
b1 Q
b1001100100 R
b1000000000 &
b1000000000 @
b1011 E
1?
0,
b1 G
19
#13300
1$
1#
0?
b10 G
0I
b10 Q
09
#13350
1*
1)
12
13
#13450
b10110 B
b11000 A
b10110 L
b1000 K
b101011010 R
b11110110 &
b11110110 @
b1010 E
b1101011010 T
b1011110110 %
b1011110110 J
b1010 O
0$
0#
1.
1/
#13500
0*
0)
02
03
#13600
1$
1#
0.
0/
#13650
1*
1)
12
13
#13750
b10001 B
b11100 A
b10001 L
b1100 K
b11010101 R
b1110001 &
b1110001 @
b1001 E
b1011010101 T
b1001110001 %
b1001110001 J
b1001 O
0$
0#
1.
1/
#13800
0*
0)
02
03
#13900
1$
1#
0.
0/
#13950
1*
1)
12
13
#14050
b1 B
b11101 A
b1 L
b1101 K
b10100101 R
b1000001 &
b1000001 @
b1000 E
b1010100101 T
b1001000001 %
b1001000001 J
b1000 O
0$
0#
1.
1/
#14100
0*
0)
02
03
#14200
1$
1#
0.
0/
#14250
1*
1)
12
13
#14350
b101 B
b11110 A
b101 L
b1110 K
b10001001 R
b100101 &
b100101 @
b111 E
b1010001001 T
b1000100101 %
b1000100101 J
b111 O
0$
0#
1.
1/
#14400
0*
0)
02
03
#14500
1$
1#
0.
0/
#14550
1*
1)
12
13
#14650
b10101 B
b11111 A
b10101 L
b1111 K
b1111001 R
b10101 &
b10101 @
b110 E
b1001111001 T
b1000010101 %
b1000010101 J
b110 O
0$
0#
1.
1/
#14700
0*
0)
02
03
#14800
1$
1#
0.
0/
#14850
1*
1)
12
13
#14950
b1101 B
b1101 L
b1110001 R
b1101 &
b1101 @
b101 E
b1001110001 T
b1000001101 %
b1000001101 J
b101 O
0$
0#
1.
1/
#15000
0*
0)
02
03
#15100
1$
1#
0.
0/
#15150
1*
1)
12
13
#15250
b111 B
b111 L
b1101011 R
b111 &
b111 @
b100 E
b1001101011 T
b1000000111 %
b1000000111 J
b100 O
0$
0#
1.
1/
#15300
0*
0)
02
03
#15400
1$
1#
0.
0/
#15450
1*
1)
12
13
#15550
b100 B
b100 L
b1101000 R
b100 &
b100 @
b11 E
b1001101000 T
b1000000100 %
b1000000100 J
b11 O
0$
0#
1.
1/
#15600
0*
0)
02
03
#15700
1$
1#
0.
0/
#15750
1*
1)
12
13
#15850
b10 B
b10 L
b1100110 R
b10 &
b10 @
b10 E
b1001100110 T
b1000000010 %
b1000000010 J
b10 O
0$
0#
1.
1/
#15900
0*
0)
02
03
#16000
1$
1#
0.
0/
#16050
1*
1)
12
13
#16150
b1 E
b1 O
0$
0#
1.
1/
#16200
0*
0)
02
03
#16300
1$
1#
0.
0/
#16350
1*
1)
12
13
#16450
b1 B
b1 L
b1100101 R
b1 &
b1 @
b0 E
b1001100101 T
b1000000001 %
b1000000001 J
b0 O
0$
0#
1.
1/
#16500
0*
0)
02
03
#16600
1$
1#
0.
0/
#16650
1*
1)
12
13
#16750
1,
b11 G
1+
b11 Q
0$
0#
1.
1/
#16800
0*
0)
02
03
#16900
0.
0/
#17300
b11 4
b11 7
b11 S
b11 U
b0 5
#17400
b0 B
b1111 A
b0 L
b11111 K
b1001100100 R
b1000000000 &
b1000000000 @
b1011 E
1?
0,
b1 G
b1100100 T
b0 %
b0 J
b1011 O
1I
0+
b1 Q
19
#17500
1#
1$
0I
b10 Q
0?
b10 G
09
#17550
1)
1*
13
12
#17650
b10110 L
b1000 K
b10110 B
b11000 A
b1101011010 T
b1011110110 %
b1011110110 J
b1010 O
b101011010 R
b11110110 &
b11110110 @
b1010 E
0#
0$
1/
1.
#17700
0)
0*
03
02
#17800
1#
1$
0/
0.
#17850
1)
1*
13
12
#17950
b10001 L
b1100 K
b10001 B
b11100 A
b1011010101 T
b1001110001 %
b1001110001 J
b1001 O
b11010101 R
b1110001 &
b1110001 @
b1001 E
0#
0$
1/
1.
#18000
0)
0*
03
02
#18100
1#
1$
0/
0.
#18150
1)
1*
13
12
#18250
b1 L
b1101 K
b1 B
b11101 A
b1010100101 T
b1001000001 %
b1001000001 J
b1000 O
b10100101 R
b1000001 &
b1000001 @
b1000 E
0#
0$
1/
1.
#18300
0)
0*
03
02
#18400
1#
1$
0/
0.
#18450
1)
1*
13
12
#18550
b101 L
b1110 K
b101 B
b11110 A
b1010001001 T
b1000100101 %
b1000100101 J
b111 O
b10001001 R
b100101 &
b100101 @
b111 E
0#
0$
1/
1.
#18600
0)
0*
03
02
#18700
1#
1$
0/
0.
#18750
1)
1*
13
12
#18850
b10101 L
b1111 K
b10101 B
b11111 A
b1001111001 T
b1000010101 %
b1000010101 J
b110 O
b1111001 R
b10101 &
b10101 @
b110 E
0#
0$
1/
1.
#18900
0)
0*
03
02
#19000
1#
1$
0/
0.
#19050
1)
1*
13
12
#19150
b1101 L
b1101 B
b1001110001 T
b1000001101 %
b1000001101 J
b101 O
b1110001 R
b1101 &
b1101 @
b101 E
0#
0$
1/
1.
#19200
0)
0*
03
02
#19300
1#
1$
0/
0.
#19350
1)
1*
13
12
#19450
b111 L
b111 B
b1001101011 T
b1000000111 %
b1000000111 J
b100 O
b1101011 R
b111 &
b111 @
b100 E
0#
0$
1/
1.
#19500
0)
0*
03
02
#19600
1#
1$
0/
0.
#19650
1)
1*
13
12
#19750
b100 L
b100 B
b1001101000 T
b1000000100 %
b1000000100 J
b11 O
b1101000 R
b100 &
b100 @
b11 E
0#
0$
1/
1.
#19800
0)
0*
03
02
#19900
1#
1$
0/
0.
#19950
1)
1*
13
12
#20050
b10 L
b10 B
b1001100110 T
b1000000010 %
b1000000010 J
b10 O
b1100110 R
b10 &
b10 @
b10 E
0#
0$
1/
1.
#20100
0)
0*
03
02
#20200
1#
1$
0/
0.
#20250
1)
1*
13
12
#20350
b1 O
b1 E
0#
0$
1/
1.
#20400
0)
0*
03
02
#20500
1#
1$
0/
0.
#20550
1)
1*
13
12
#20650
b1 L
b1 B
b1001100101 T
b1000000001 %
b1000000001 J
b0 O
b1100101 R
b1 &
b1 @
b0 E
0#
0$
1/
1.
#20700
0)
0*
03
02
#20800
1#
1$
0/
0.
#20850
1)
1*
13
12
#20950
1+
b11 Q
1,
b11 G
0#
0$
1/
1.
#21000
0)
0*
03
02
#21100
0/
0.
#21500
b100 4
b100 7
b100 S
b100 U
b0 5
#21600
b0 L
b11111 K
b0 B
b1111 A
b1100100 T
b0 %
b0 J
b1011 O
1I
0+
b1 Q
b1001100100 R
b1000000000 &
b1000000000 @
b1011 E
1?
0,
b1 G
19
#21700
1$
1#
0?
b10 G
0I
b10 Q
09
#21750
1*
1)
12
13
#21850
b10110 B
b11000 A
b10110 L
b1000 K
b101011010 R
b11110110 &
b11110110 @
b1010 E
b1101011010 T
b1011110110 %
b1011110110 J
b1010 O
0$
0#
1.
1/
#21900
0*
0)
02
03
#22000
1$
1#
0.
0/
#22050
1*
1)
12
13
#22150
b10001 B
b11100 A
b10001 L
b1100 K
b11010101 R
b1110001 &
b1110001 @
b1001 E
b1011010101 T
b1001110001 %
b1001110001 J
b1001 O
0$
0#
1.
1/
#22200
0*
0)
02
03
#22300
1$
1#
0.
0/
#22350
1*
1)
12
13
#22450
b1 B
b11101 A
b1 L
b1101 K
b10100101 R
b1000001 &
b1000001 @
b1000 E
b1010100101 T
b1001000001 %
b1001000001 J
b1000 O
0$
0#
1.
1/
#22500
0*
0)
02
03
#22600
1$
1#
0.
0/
#22650
1*
1)
12
13
#22750
b101 B
b11110 A
b101 L
b1110 K
b10001001 R
b100101 &
b100101 @
b111 E
b1010001001 T
b1000100101 %
b1000100101 J
b111 O
0$
0#
1.
1/
#22800
0*
0)
02
03
#22900
1$
1#
0.
0/
#22950
1*
1)
12
13
#23050
b10101 B
b11111 A
b10101 L
b1111 K
b1111001 R
b10101 &
b10101 @
b110 E
b1001111001 T
b1000010101 %
b1000010101 J
b110 O
0$
0#
1.
1/
#23100
0*
0)
02
03
#23200
1$
1#
0.
0/
#23250
1*
1)
12
13
#23350
b1101 B
b1101 L
b1110001 R
b1101 &
b1101 @
b101 E
b1001110001 T
b1000001101 %
b1000001101 J
b101 O
0$
0#
1.
1/
#23400
0*
0)
02
03
#23500
1$
1#
0.
0/
#23550
1*
1)
12
13
#23650
b111 B
b111 L
b1101011 R
b111 &
b111 @
b100 E
b1001101011 T
b1000000111 %
b1000000111 J
b100 O
0$
0#
1.
1/
#23700
0*
0)
02
03
#23800
1$
1#
0.
0/
#23850
1*
1)
12
13
#23950
b100 B
b100 L
b1101000 R
b100 &
b100 @
b11 E
b1001101000 T
b1000000100 %
b1000000100 J
b11 O
0$
0#
1.
1/
#24000
0*
0)
02
03
#24100
1$
1#
0.
0/
#24150
1*
1)
12
13
