adc_hdl/adc_fsm_10b_real/conditional_offset.v
module conditional_offset( vin, 
                           vout,
                           offset);

   input [9:0] vin, offset;
   output [9:0] vout;
   
   reg [9:0] vout;
   reg [9:0] flipped_offset;
   
   always @ (*) begin
      flipped_offset = ~offset + 10'd1;
      
      if (offset[9]) begin // if negative number
         if (vin > flipped_offset)
            vout = vin - flipped_offset;
         else
            vout = 10'd0;  // set a floor at 0
      end
      else begin           // if positive number
         if (vin < (10'd 1023 - offset))
            vout = vin + offset;
         else
            vout = 10'd1023;
      end
   end
endmodule

adc_hdl/adc_fsm_10b_real/testbench_conditional_offset.v
`timescale 100ns/1ns

module testbench_conditional_offset;
   reg [9:0] vin = 0;
   reg [9:0] vout_reg = 0;
   reg [9:0] offset = -10;
   
   reg [10:0] index = 0;
   wire [9:0] vout;
   integer textfile1 = 0;
   
   conditional_offset block1( .vin(vin), 
                              .vout(vout),
                              .offset(offset));
   
   always @ (*) begin
      vout_reg = vout;
   end
   
   
   initial begin
      textfile1 = $fopen("offset_handling.csv","w");
      $fwrite(textfile1,"vin,osc,vout,\n");
      $dumpfile("log_offset_handling.vcd");
		$dumpvars;
      
      for (index=0; index<1024; index = index + 1) begin
         #1 $fwrite(textfile1,"%d,%d,%d\n",vin,offset,vout_reg);
         #1 vin = vin + 1;
      end
      
      #1 $fclose(textfile1);
      #10 $finish;
   end
   
endmodule

adc_hdl/adc_fsm_10b_real/log_offset_handling.vcd
$date
	Tue Dec 31 17:47:00 2019
$end
$version
	Icarus Verilog
$end
$timescale
	1ns
$end
$scope module testbench_conditional_offset $end
$var wire 10 ! vout [9:0] $end
$var reg 11 " index [10:0] $end
$var reg 10 # offset [9:0] $end
$var reg 10 $ vin [9:0] $end
$var reg 10 % vout_reg [9:0] $end
$var integer 32 & textfile1 [31:0] $end
$scope module block1 $end
$var wire 10 ' offset [9:0] $end
$var wire 10 ( vin [9:0] $end
$var reg 10 ) flipped_offset [9:0] $end
$var reg 10 * vout [9:0] $end
$upscope $end
$upscope $end
$enddefinitions $end
#0
$dumpvars
b0 *
b1010 )
b0 (
b1111110110 '
b10000000000000000000000000000011 &
b0 %
b0 $
b1111110110 #
b0 "
b0 !
$end
#200
b1 "
b1 $
b1 (
#400
b10 "
b10 $
b10 (
#600
b11 "
b11 $
b11 (
#800
b100 "
b100 $
b100 (
#1000
b101 "
b101 $
b101 (
#1200
b110 "
b110 $
b110 (
#1400
b111 "
b111 $
b111 (
#1600
b1000 "
b1000 $
b1000 (
#1800
b1001 "
b1001 $
b1001 (
#2000
b1010 "
b1010 $
b1010 (
#2200
b1 %
b1 !
b1 *
b1011 "
b1011 $
b1011 (
#2400
b10 %
b10 !
b10 *
b1100 "
b1100 $
b1100 (
#2600
b11 %
b11 !
b11 *
b1101 "
b1101 $
b1101 (
#2800
b100 %
b100 !
b100 *
b1110 "
b1110 $
b1110 (
#3000
b101 %
b101 !
b101 *
b1111 "
b1111 $
b1111 (
#3200
b110 %
b110 !
b110 *
b10000 "
b10000 $
b10000 (
#3400
b111 %
b111 !
b111 *
b10001 "
b10001 $
b10001 (
#3600
b1000 %
b1000 !
b1000 *
b10010 "
b10010 $
b10010 (
#3800
b1001 %
b1001 !
b1001 *
b10011 "
b10011 $
b10011 (
#4000
b1010 %
b1010 !
b1010 *
b10100 "
b10100 $
b10100 (
#4200
b1011 %
b1011 !
b1011 *
b10101 "
b10101 $
b10101 (
#4400
b1100 %
b1100 !
b1100 *
b10110 "
b10110 $
b10110 (
#4600
b1101 %
b1101 !
b1101 *
b10111 "
b10111 $
b10111 (
#4800
b1110 %
b1110 !
b1110 *
b11000 "
b11000 $
b11000 (
#5000
b1111 %
b1111 !
b1111 *
b11001 "
b11001 $
b11001 (
#5200
b10000 %
b10000 !
b10000 *
b11010 "
b11010 $
b11010 (
#5400
b10001 %
b10001 !
b10001 *
b11011 "
b11011 $
b11011 (
#5600
b10010 %
b10010 !
b10010 *
b11100 "
b11100 $
b11100 (
#5800
b10011 %
b10011 !
b10011 *
b11101 "
b11101 $
b11101 (
#6000
b10100 %
b10100 !
b10100 *
b11110 "
b11110 $
b11110 (
#6200
b10101 %
b10101 !
b10101 *
b11111 "
b11111 $
b11111 (
#6400
b10110 %
b10110 !
b10110 *
b100000 "
b100000 $
b100000 (
#6600
b10111 %
b10111 !
b10111 *
b100001 "
b100001 $
b100001 (
#6800
b11000 %
b11000 !
b11000 *
b100010 "
b100010 $
b100010 (
#7000
b11001 %
b11001 !
b11001 *
b100011 "
b100011 $
b100011 (
#7200
b11010 %
b11010 !
b11010 *
b100100 "
b100100 $
b100100 (
#7400
b11011 %
b11011 !
b11011 *
b100101 "
b100101 $
b100101 (
#7600
b11100 %
b11100 !
b11100 *
b100110 "
b100110 $
b100110 (
#7800
b11101 %
b11101 !
b11101 *
b100111 "
b100111 $
b100111 (
#8000
b11110 %
b11110 !
b11110 *
b101000 "
b101000 $
b101000 (
#8200
b11111 %
b11111 !
b11111 *
b101001 "
b101001 $
b101001 (
#8400
b100000 %
b100000 !
b100000 *
b101010 "
b101010 $
b101010 (
#8600
b100001 %
b100001 !
b100001 *
b101011 "
b101011 $
b101011 (
#8800
b100010 %
b100010 !
b100010 *
b101100 "
b101100 $
b101100 (
#9000
b100011 %
b100011 !
b100011 *
b101101 "
b101101 $
b101101 (
#9200
b100100 %
b100100 !
b100100 *
b101110 "
b101110 $
b101110 (
#9400
b100101 %
b100101 !
b100101 *
b101111 "
b101111 $
b101111 (
#9600
b100110 %
b100110 !
b100110 *
b110000 "
b110000 $
b110000 (
#9800
b100111 %
b100111 !
b100111 *
b110001 "
b110001 $
b110001 (
#10000
b101000 %
b101000 !
b101000 *
b110010 "
b110010 $
b110010 (
#10200
b101001 %
b101001 !
b101001 *
b110011 "
b110011 $
b110011 (
#10400
b101010 %
b101010 !
b101010 *
b110100 "
b110100 $
b110100 (
#10600
b101011 %
b101011 !
b101011 *
b110101 "
b110101 $
b110101 (
#10800
b101100 %
b101100 !
b101100 *
b110110 "
b110110 $
b110110 (
#11000
b101101 %
b101101 !
b101101 *
b110111 "
b110111 $
b110111 (
#11200
b101110 %
b101110 !
b101110 *
b111000 "
b111000 $
b111000 (
#11400
b101111 %
b101111 !
b101111 *
b111001 "
b111001 $
b111001 (
#11600
b110000 %
b110000 !
b110000 *
b111010 "
b111010 $
b111010 (
#11800
b110001 %
b110001 !
b110001 *
b111011 "
b111011 $
b111011 (
#12000
b110010 %
b110010 !
b110010 *
b111100 "
b111100 $
b111100 (
#12200
b110011 %
b110011 !
b110011 *
b111101 "
b111101 $
b111101 (
#12400
b110100 %
b110100 !
b110100 *
b111110 "
b111110 $
b111110 (
#12600
b110101 %
b110101 !
b110101 *
b111111 "
b111111 $
b111111 (
#12800
b110110 %
b110110 !
b110110 *
b1000000 "
b1000000 $
b1000000 (
#13000
b110111 %
b110111 !
b110111 *
b1000001 "
b1000001 $
b1000001 (
#13200
b111000 %
b111000 !
b111000 *
b1000010 "
b1000010 $
b1000010 (
#13400
b111001 %
b111001 !
b111001 *
b1000011 "
b1000011 $
b1000011 (
#13600
b111010 %
b111010 !
b111010 *
b1000100 "
b1000100 $
b1000100 (
#13800
b111011 %
b111011 !
b111011 *
b1000101 "
b1000101 $
b1000101 (
#14000
b111100 %
b111100 !
b111100 *
b1000110 "
b1000110 $
b1000110 (
#14200
b111101 %
b111101 !
b111101 *
b1000111 "
b1000111 $
b1000111 (
#14400
b111110 %
b111110 !
b111110 *
b1001000 "
b1001000 $
b1001000 (
#14600
b111111 %
b111111 !
b111111 *
b1001001 "
b1001001 $
b1001001 (
#14800
b1000000 %
b1000000 !
b1000000 *
b1001010 "
b1001010 $
b1001010 (
#15000
b1000001 %
b1000001 !
b1000001 *
b1001011 "
b1001011 $
b1001011 (
#15200
b1000010 %
b1000010 !
b1000010 *
b1001100 "
b1001100 $
b1001100 (
#15400
b1000011 %
b1000011 !
b1000011 *
b1001101 "
b1001101 $
b1001101 (
#15600
b1000100 %
b1000100 !
b1000100 *
b1001110 "
b1001110 $
b1001110 (
#15800
b1000101 %
b1000101 !
b1000101 *
b1001111 "
b1001111 $
b1001111 (
#16000
b1000110 %
b1000110 !
b1000110 *
b1010000 "
b1010000 $
b1010000 (
#16200
b1000111 %
b1000111 !
b1000111 *
b1010001 "
b1010001 $
b1010001 (
#16400
b1001000 %
b1001000 !
b1001000 *
b1010010 "
b1010010 $
b1010010 (
#16600
b1001001 %
b1001001 !
b1001001 *
b1010011 "
b1010011 $
b1010011 (
#16800
b1001010 %
b1001010 !
b1001010 *
b1010100 "
b1010100 $
b1010100 (
#17000
b1001011 %
b1001011 !
b1001011 *
b1010101 "
b1010101 $
b1010101 (
#17200
b1001100 %
b1001100 !
b1001100 *
b1010110 "
b1010110 $
b1010110 (
#17400
b1001101 %
b1001101 !
b1001101 *
b1010111 "
b1010111 $
b1010111 (
#17600
b1001110 %
b1001110 !
b1001110 *
b1011000 "
b1011000 $
b1011000 (
#17800
b1001111 %
b1001111 !
b1001111 *
b1011001 "
b1011001 $
b1011001 (
#18000
b1010000 %
b1010000 !
b1010000 *
b1011010 "
b1011010 $
b1011010 (
#18200
b1010001 %
b1010001 !
b1010001 *
b1011011 "
b1011011 $
b1011011 (
#18400
b1010010 %
b1010010 !
b1010010 *
b1011100 "
b1011100 $
b1011100 (
#18600
b1010011 %
b1010011 !
b1010011 *
b1011101 "
b1011101 $
b1011101 (
#18800
b1010100 %
b1010100 !
b1010100 *
b1011110 "
b1011110 $
b1011110 (
#19000
b1010101 %
b1010101 !
b1010101 *
b1011111 "
b1011111 $
b1011111 (
#19200
b1010110 %
b1010110 !
b1010110 *
b1100000 "
b1100000 $
b1100000 (
#19400
b1010111 %
b1010111 !
b1010111 *
b1100001 "
b1100001 $
b1100001 (
#19600
b1011000 %
b1011000 !
b1011000 *
b1100010 "
b1100010 $
b1100010 (
#19800
b1011001 %
b1011001 !
b1011001 *
b1100011 "
b1100011 $
b1100011 (
#20000
b1011010 %
b1011010 !
b1011010 *
b1100100 "
b1100100 $
b1100100 (
#20200
b1011011 %
b1011011 !
b1011011 *
b1100101 "
b1100101 $
b1100101 (
#20400
b1011100 %
b1011100 !
b1011100 *
b1100110 "
b1100110 $
b1100110 (
#20600
b1011101 %
b1011101 !
b1011101 *
b1100111 "
b1100111 $
b1100111 (
#20800
b1011110 %
b1011110 !
b1011110 *
b1101000 "
b1101000 $
b1101000 (
#21000
b1011111 %
b1011111 !
b1011111 *
b1101001 "
b1101001 $
b1101001 (
#21200
b1100000 %
b1100000 !
b1100000 *
b1101010 "
b1101010 $
b1101010 (
#21400
b1100001 %
b1100001 !
b1100001 *
b1101011 "
b1101011 $
b1101011 (
#21600
b1100010 %
b1100010 !
b1100010 *
b1101100 "
b1101100 $
b1101100 (
#21800
b1100011 %
b1100011 !
b1100011 *
b1101101 "
b1101101 $
b1101101 (
#22000
b1100100 %
b1100100 !
b1100100 *
b1101110 "
b1101110 $
b1101110 (
#22200
b1100101 %
b1100101 !
b1100101 *
b1101111 "
b1101111 $
b1101111 (
#22400
b1100110 %
b1100110 !
b1100110 *
b1110000 "
b1110000 $
b1110000 (
#22600
b1100111 %
b1100111 !
b1100111 *
b1110001 "
b1110001 $
b1110001 (
#22800
b1101000 %
b1101000 !
b1101000 *
b1110010 "
b1110010 $
b1110010 (
#23000
b1101001 %
b1101001 !
b1101001 *
b1110011 "
b1110011 $
b1110011 (
#23200
b1101010 %
b1101010 !
b1101010 *
b1110100 "
b1110100 $
b1110100 (
#23400
b1101011 %
b1101011 !
b1101011 *
b1110101 "
b1110101 $
b1110101 (
#23600
b1101100 %
b1101100 !
b1101100 *
b1110110 "
b1110110 $
b1110110 (
#23800
b1101101 %
b1101101 !
b1101101 *
b1110111 "
b1110111 $
b1110111 (
#24000
b1101110 %
b1101110 !
b1101110 *
b1111000 "
b1111000 $
b1111000 (
#24200
b1101111 %
b1101111 !
b1101111 *
b1111001 "
b1111001 $
b1111001 (
#24400
b1110000 %
b1110000 !
b1110000 *
b1111010 "
b1111010 $
b1111010 (
#24600
b1110001 %
b1110001 !
b1110001 *
b1111011 "
b1111011 $
b1111011 (
#24800
b1110010 %
b1110010 !
b1110010 *
b1111100 "
b1111100 $
b1111100 (
#25000
b1110011 %
b1110011 !
b1110011 *
b1111101 "
b1111101 $
b1111101 (
#25200
b1110100 %
b1110100 !
b1110100 *
b1111110 "
b1111110 $
b1111110 (
#25400
b1110101 %
b1110101 !
b1110101 *
b1111111 "
b1111111 $
b1111111 (
#25600
b1110110 %
b1110110 !
b1110110 *
b10000000 "
b10000000 $
b10000000 (
#25800
b1110111 %
b1110111 !
b1110111 *
b10000001 "
b10000001 $
b10000001 (
#26000
b1111000 %
b1111000 !
b1111000 *
b10000010 "
b10000010 $
b10000010 (
#26200
b1111001 %
b1111001 !
b1111001 *
b10000011 "
b10000011 $
b10000011 (
#26400
b1111010 %
b1111010 !
b1111010 *
b10000100 "
b10000100 $
b10000100 (
#26600
b1111011 %
b1111011 !
b1111011 *
b10000101 "
b10000101 $
b10000101 (
#26800
b1111100 %
b1111100 !
b1111100 *
b10000110 "
b10000110 $
b10000110 (
#27000
b1111101 %
b1111101 !
b1111101 *
b10000111 "
b10000111 $
b10000111 (
#27200
b1111110 %
b1111110 !
b1111110 *
b10001000 "
b10001000 $
b10001000 (
#27400
b1111111 %
b1111111 !
b1111111 *
b10001001 "
b10001001 $
b10001001 (
#27600
b10000000 %
b10000000 !
b10000000 *
b10001010 "
b10001010 $
b10001010 (
#27800
b10000001 %
b10000001 !
b10000001 *
b10001011 "
b10001011 $
b10001011 (
#28000
b10000010 %
b10000010 !
b10000010 *
b10001100 "
b10001100 $
b10001100 (
#28200
b10000011 %
b10000011 !
b10000011 *
b10001101 "
b10001101 $
b10001101 (
#28400
b10000100 %
b10000100 !
b10000100 *
b10001110 "
b10001110 $
b10001110 (
#28600
b10000101 %
b10000101 !
b10000101 *
b10001111 "
b10001111 $
b10001111 (
#28800
b10000110 %
b10000110 !
b10000110 *
b10010000 "
b10010000 $
b10010000 (
#29000
b10000111 %
b10000111 !
b10000111 *
b10010001 "
b10010001 $
b10010001 (
#29200
b10001000 %
b10001000 !
b10001000 *
b10010010 "
b10010010 $
b10010010 (
#29400
b10001001 %
b10001001 !
b10001001 *
b10010011 "
b10010011 $
b10010011 (
#29600
b10001010 %
b10001010 !
b10001010 *
b10010100 "
b10010100 $
b10010100 (
#29800
b10001011 %
b10001011 !
b10001011 *
b10010101 "
b10010101 $
b10010101 (
#30000
b10001100 %
b10001100 !
b10001100 *
b10010110 "
b10010110 $
b10010110 (
#30200
b10001101 %
b10001101 !
b10001101 *
b10010111 "
b10010111 $
b10010111 (
#30400
b10001110 %
b10001110 !
b10001110 *
b10011000 "
b10011000 $
b10011000 (
#30600
b10001111 %
b10001111 !
b10001111 *
b10011001 "
b10011001 $
b10011001 (
#30800
b10010000 %
b10010000 !
b10010000 *
b10011010 "
b10011010 $
b10011010 (
#31000
b10010001 %
b10010001 !
b10010001 *
b10011011 "
b10011011 $
b10011011 (
#31200
b10010010 %
b10010010 !
b10010010 *
b10011100 "
b10011100 $
b10011100 (
#31400
b10010011 %
b10010011 !
b10010011 *
b10011101 "
b10011101 $
b10011101 (
#31600
b10010100 %
b10010100 !
b10010100 *
b10011110 "
b10011110 $
b10011110 (
#31800
b10010101 %
b10010101 !
b10010101 *
b10011111 "
b10011111 $
b10011111 (
#32000
b10010110 %
b10010110 !
b10010110 *
b10100000 "
b10100000 $
b10100000 (
#32200
b10010111 %
b10010111 !
b10010111 *
b10100001 "
b10100001 $
b10100001 (
#32400
b10011000 %
b10011000 !
b10011000 *
b10100010 "
b10100010 $
b10100010 (
#32600
b10011001 %
b10011001 !
b10011001 *
b10100011 "
b10100011 $
b10100011 (
#32800
b10011010 %
b10011010 !
b10011010 *
b10100100 "
b10100100 $
b10100100 (
#33000
b10011011 %
b10011011 !
b10011011 *
b10100101 "
b10100101 $
b10100101 (
#33200
b10011100 %
b10011100 !
b10011100 *
b10100110 "
b10100110 $
b10100110 (
#33400
b10011101 %
b10011101 !
b10011101 *
b10100111 "
b10100111 $
b10100111 (
#33600
b10011110 %
b10011110 !
b10011110 *
b10101000 "
b10101000 $
b10101000 (
#33800
b10011111 %
b10011111 !
b10011111 *
b10101001 "
b10101001 $
b10101001 (
#34000
b10100000 %
b10100000 !
b10100000 *
b10101010 "
b10101010 $
b10101010 (
#34200
b10100001 %
b10100001 !
b10100001 *
b10101011 "
b10101011 $
b10101011 (
#34400
b10100010 %
b10100010 !
b10100010 *
b10101100 "
b10101100 $
b10101100 (
#34600
b10100011 %
b10100011 !
b10100011 *
b10101101 "
b10101101 $
b10101101 (
#34800
b10100100 %
b10100100 !
b10100100 *
b10101110 "
b10101110 $
b10101110 (
#35000
b10100101 %
b10100101 !
b10100101 *
b10101111 "
b10101111 $
b10101111 (
#35200
b10100110 %
b10100110 !
b10100110 *
b10110000 "
b10110000 $
b10110000 (
#35400
b10100111 %
b10100111 !
b10100111 *
b10110001 "
b10110001 $
b10110001 (
#35600
b10101000 %
b10101000 !
b10101000 *
b10110010 "
b10110010 $
b10110010 (
#35800
b10101001 %
b10101001 !
b10101001 *
b10110011 "
b10110011 $
b10110011 (
#36000
b10101010 %
b10101010 !
b10101010 *
b10110100 "
b10110100 $
b10110100 (
#36200
b10101011 %
b10101011 !
b10101011 *
b10110101 "
b10110101 $
b10110101 (
#36400
b10101100 %
b10101100 !
b10101100 *
b10110110 "
b10110110 $
b10110110 (
#36600
b10101101 %
b10101101 !
b10101101 *
b10110111 "
b10110111 $
b10110111 (
#36800
b10101110 %
b10101110 !
b10101110 *
b10111000 "
b10111000 $
b10111000 (
#37000
b10101111 %
b10101111 !
b10101111 *
b10111001 "
b10111001 $
b10111001 (
#37200
b10110000 %
b10110000 !
b10110000 *
b10111010 "
b10111010 $
b10111010 (
#37400
b10110001 %
b10110001 !
b10110001 *
b10111011 "
b10111011 $
b10111011 (
#37600
b10110010 %
b10110010 !
b10110010 *
b10111100 "
b10111100 $
b10111100 (
#37800
b10110011 %
b10110011 !
b10110011 *
b10111101 "
b10111101 $
b10111101 (
#38000
b10110100 %
b10110100 !
b10110100 *
b10111110 "
b10111110 $
b10111110 (
#38200
b10110101 %
b10110101 !
b10110101 *
b10111111 "
b10111111 $
b10111111 (
#38400
b10110110 %
b10110110 !
b10110110 *
b11000000 "
b11000000 $
b11000000 (
#38600
b10110111 %
b10110111 !
b10110111 *
b11000001 "
b11000001 $
b11000001 (
#38800
b10111000 %
b10111000 !
b10111000 *
b11000010 "
b11000010 $
b11000010 (
#39000
b10111001 %
b10111001 !
b10111001 *
b11000011 "
b11000011 $
b11000011 (
#39200
b10111010 %
b10111010 !
b10111010 *
b11000100 "
b11000100 $
b11000100 (
#39400
b10111011 %
b10111011 !
b10111011 *
b11000101 "
b11000101 $
b11000101 (
#39600
b10111100 %
b10111100 !
b10111100 *
b11000110 "
b11000110 $
b11000110 (
#39800
b10111101 %
b10111101 !
b10111101 *
b11000111 "
b11000111 $
b11000111 (
#40000
b10111110 %
b10111110 !
b10111110 *
b11001000 "
b11001000 $
b11001000 (
#40200
b10111111 %
b10111111 !
b10111111 *
b11001001 "
b11001001 $
b11001001 (
#40400
b11000000 %
b11000000 !
b11000000 *
b11001010 "
b11001010 $
b11001010 (
#40600
b11000001 %
b11000001 !
b11000001 *
b11001011 "
b11001011 $
b11001011 (
#40800
b11000010 %
b11000010 !
b11000010 *
b11001100 "
b11001100 $
b11001100 (
#41000
b11000011 %
b11000011 !
b11000011 *
b11001101 "
b11001101 $
b11001101 (
#41200
b11000100 %
b11000100 !
b11000100 *
b11001110 "
b11001110 $
b11001110 (
#41400
b11000101 %
b11000101 !
b11000101 *
b11001111 "
b11001111 $
b11001111 (
#41600
b11000110 %
b11000110 !
b11000110 *
b11010000 "
b11010000 $
b11010000 (
#41800
b11000111 %
b11000111 !
b11000111 *
b11010001 "
b11010001 $
b11010001 (
#42000
b11001000 %
b11001000 !
b11001000 *
b11010010 "
b11010010 $
b11010010 (
#42200
b11001001 %
b11001001 !
b11001001 *
b11010011 "
b11010011 $
b11010011 (
#42400
b11001010 %
b11001010 !
b11001010 *
b11010100 "
b11010100 $
b11010100 (
#42600
b11001011 %
b11001011 !
b11001011 *
b11010101 "
b11010101 $
b11010101 (
#42800
b11001100 %
b11001100 !
b11001100 *
b11010110 "
b11010110 $
b11010110 (
#43000
b11001101 %
b11001101 !
b11001101 *
b11010111 "
b11010111 $
b11010111 (
#43200
b11001110 %
b11001110 !
b11001110 *
b11011000 "
b11011000 $
b11011000 (
#43400
b11001111 %
b11001111 !
b11001111 *
b11011001 "
b11011001 $
b11011001 (
#43600
b11010000 %
b11010000 !
b11010000 *
b11011010 "
b11011010 $
b11011010 (
#43800
b11010001 %
b11010001 !
b11010001 *
b11011011 "
b11011011 $
b11011011 (
#44000
b11010010 %
b11010010 !
b11010010 *
b11011100 "
b11011100 $
b11011100 (
#44200
b11010011 %
b11010011 !
b11010011 *
b11011101 "
b11011101 $
b11011101 (
#44400
b11010100 %
b11010100 !
b11010100 *
b11011110 "
b11011110 $
b11011110 (
#44600
b11010101 %
b11010101 !
b11010101 *
b11011111 "
b11011111 $
b11011111 (
#44800
b11010110 %
b11010110 !
b11010110 *
b11100000 "
b11100000 $
b11100000 (
#45000
b11010111 %
b11010111 !
b11010111 *
b11100001 "
b11100001 $
b11100001 (
#45200
b11011000 %
b11011000 !
b11011000 *
b11100010 "
b11100010 $
b11100010 (
#45400
b11011001 %
b11011001 !
b11011001 *
b11100011 "
b11100011 $
b11100011 (
#45600
b11011010 %
b11011010 !
b11011010 *
b11100100 "
b11100100 $
b11100100 (
#45800
b11011011 %
b11011011 !
b11011011 *
b11100101 "
b11100101 $
b11100101 (
#46000
b11011100 %
b11011100 !
b11011100 *
b11100110 "
b11100110 $
b11100110 (
#46200
b11011101 %
b11011101 !
b11011101 *
b11100111 "
b11100111 $
b11100111 (
#46400
b11011110 %
b11011110 !
b11011110 *
b11101000 "
b11101000 $
b11101000 (
#46600
b11011111 %
b11011111 !
b11011111 *
b11101001 "
b11101001 $
b11101001 (
#46800
b11100000 %
b11100000 !
b11100000 *
b11101010 "
b11101010 $
b11101010 (
#47000
b11100001 %
b11100001 !
b11100001 *
b11101011 "
b11101011 $
b11101011 (
#47200
b11100010 %
b11100010 !
b11100010 *
b11101100 "
b11101100 $
b11101100 (
#47400
b11100011 %
b11100011 !
b11100011 *
b11101101 "
b11101101 $
b11101101 (
#47600
b11100100 %
b11100100 !
b11100100 *
b11101110 "
b11101110 $
b11101110 (
#47800
b11100101 %
b11100101 !
b11100101 *
b11101111 "
b11101111 $
b11101111 (
#48000
b11100110 %
b11100110 !
b11100110 *
b11110000 "
b11110000 $
b11110000 (
#48200
b11100111 %
b11100111 !
b11100111 *
b11110001 "
b11110001 $
b11110001 (
#48400
b11101000 %
b11101000 !
b11101000 *
b11110010 "
b11110010 $
b11110010 (
#48600
b11101001 %
b11101001 !
b11101001 *
b11110011 "
b11110011 $
b11110011 (
#48800
b11101010 %
b11101010 !
b11101010 *
b11110100 "
b11110100 $
b11110100 (
#49000
b11101011 %
b11101011 !
b11101011 *
b11110101 "
b11110101 $
b11110101 (
#49200
b11101100 %
b11101100 !
b11101100 *
b11110110 "
b11110110 $
b11110110 (
#49400
b11101101 %
b11101101 !
b11101101 *
b11110111 "
b11110111 $
b11110111 (
#49600
b11101110 %
b11101110 !
b11101110 *
b11111000 "
b11111000 $
b11111000 (
#49800
b11101111 %
b11101111 !
b11101111 *
b11111001 "
b11111001 $
b11111001 (
#50000
b11110000 %
b11110000 !
b11110000 *
b11111010 "
b11111010 $
b11111010 (
#50200
b11110001 %
b11110001 !
b11110001 *
b11111011 "
b11111011 $
b11111011 (
#50400
b11110010 %
b11110010 !
b11110010 *
b11111100 "
b11111100 $
b11111100 (
#50600
b11110011 %
b11110011 !
b11110011 *
b11111101 "
b11111101 $
b11111101 (
#50800
b11110100 %
b11110100 !
b11110100 *
b11111110 "
b11111110 $
b11111110 (
#51000
b11110101 %
b11110101 !
b11110101 *
b11111111 "
b11111111 $
b11111111 (
#51200
b11110110 %
b11110110 !
b11110110 *
b100000000 "
b100000000 $
b100000000 (
#51400
b11110111 %
b11110111 !
b11110111 *
b100000001 "
b100000001 $
b100000001 (
#51600
b11111000 %
b11111000 !
b11111000 *
b100000010 "
b100000010 $
b100000010 (
#51800
b11111001 %
b11111001 !
b11111001 *
b100000011 "
b100000011 $
b100000011 (
#52000
b11111010 %
b11111010 !
b11111010 *
b100000100 "
b100000100 $
b100000100 (
#52200
b11111011 %
b11111011 !
b11111011 *
b100000101 "
b100000101 $
b100000101 (
#52400
b11111100 %
b11111100 !
b11111100 *
b100000110 "
b100000110 $
b100000110 (
#52600
b11111101 %
b11111101 !
b11111101 *
b100000111 "
b100000111 $
b100000111 (
#52800
b11111110 %
b11111110 !
b11111110 *
b100001000 "
b100001000 $
b100001000 (
#53000
b11111111 %
b11111111 !
b11111111 *
b100001001 "
b100001001 $
b100001001 (
#53200
b100000000 %
b100000000 !
b100000000 *
b100001010 "
b100001010 $
b100001010 (
#53400
b100000001 %
b100000001 !
b100000001 *
b100001011 "
b100001011 $
b100001011 (
#53600
b100000010 %
b100000010 !
b100000010 *
b100001100 "
b100001100 $
b100001100 (
#53800
b100000011 %
b100000011 !
b100000011 *
b100001101 "
b100001101 $
b100001101 (
#54000
b100000100 %
b100000100 !
b100000100 *
b100001110 "
b100001110 $
b100001110 (
#54200
b100000101 %
b100000101 !
b100000101 *
b100001111 "
b100001111 $
b100001111 (
#54400
b100000110 %
b100000110 !
b100000110 *
b100010000 "
b100010000 $
b100010000 (
#54600
b100000111 %
b100000111 !
b100000111 *
b100010001 "
b100010001 $
b100010001 (
#54800
b100001000 %
b100001000 !
b100001000 *
b100010010 "
b100010010 $
b100010010 (
#55000
b100001001 %
b100001001 !
b100001001 *
b100010011 "
b100010011 $
b100010011 (
#55200
b100001010 %
b100001010 !
b100001010 *
b100010100 "
b100010100 $
b100010100 (
#55400
b100001011 %
b100001011 !
b100001011 *
b100010101 "
b100010101 $
b100010101 (
#55600
b100001100 %
b100001100 !
b100001100 *
b100010110 "
b100010110 $
b100010110 (
#55800
b100001101 %
b100001101 !
b100001101 *
b100010111 "
b100010111 $
b100010111 (
#56000
b100001110 %
b100001110 !
b100001110 *
b100011000 "
b100011000 $
b100011000 (
#56200
b100001111 %
b100001111 !
b100001111 *
b100011001 "
b100011001 $
b100011001 (
#56400
b100010000 %
b100010000 !
b100010000 *
b100011010 "
b100011010 $
b100011010 (
#56600
b100010001 %
b100010001 !
b100010001 *
b100011011 "
b100011011 $
b100011011 (
#56800
b100010010 %
b100010010 !
b100010010 *
b100011100 "
b100011100 $
b100011100 (
#57000
b100010011 %
b100010011 !
b100010011 *
b100011101 "
b100011101 $
b100011101 (
#57200
b100010100 %
b100010100 !
b100010100 *
b100011110 "
b100011110 $
b100011110 (
#57400
b100010101 %
b100010101 !
b100010101 *
b100011111 "
b100011111 $
b100011111 (
#57600
b100010110 %
b100010110 !
b100010110 *
b100100000 "
b100100000 $
b100100000 (
#57800
b100010111 %
b100010111 !
b100010111 *
b100100001 "
b100100001 $
b100100001 (
#58000
b100011000 %
b100011000 !
b100011000 *
b100100010 "
b100100010 $
b100100010 (
#58200
b100011001 %
b100011001 !
b100011001 *
b100100011 "
b100100011 $
b100100011 (
#58400
b100011010 %
b100011010 !
b100011010 *
b100100100 "
b100100100 $
b100100100 (
#58600
b100011011 %
b100011011 !
b100011011 *
b100100101 "
b100100101 $
b100100101 (
#58800
b100011100 %
b100011100 !
b100011100 *
b100100110 "
b100100110 $
b100100110 (
#59000
b100011101 %
b100011101 !
b100011101 *
b100100111 "
b100100111 $
b100100111 (
#59200
b100011110 %
b100011110 !
b100011110 *
b100101000 "
b100101000 $
b100101000 (
#59400
b100011111 %
b100011111 !
b100011111 *
b100101001 "
b100101001 $
b100101001 (
#59600
b100100000 %
b100100000 !
b100100000 *
b100101010 "
b100101010 $
b100101010 (
#59800
b100100001 %
b100100001 !
b100100001 *
b100101011 "
b100101011 $
b100101011 (
#60000
b100100010 %
b100100010 !
b100100010 *
b100101100 "
b100101100 $
b100101100 (
#60200
b100100011 %
b100100011 !
b100100011 *
b100101101 "
b100101101 $
b100101101 (
#60400
b100100100 %
b100100100 !
b100100100 *
b100101110 "
b100101110 $
b100101110 (
#60600
b100100101 %
b100100101 !
b100100101 *
b100101111 "
b100101111 $
b100101111 (
#60800
b100100110 %
b100100110 !
b100100110 *
b100110000 "
b100110000 $
b100110000 (
#61000
b100100111 %
b100100111 !
b100100111 *
b100110001 "
b100110001 $
b100110001 (
#61200
b100101000 %
b100101000 !
b100101000 *
b100110010 "
b100110010 $
b100110010 (
#61400
b100101001 %
b100101001 !
b100101001 *
b100110011 "
b100110011 $
b100110011 (
#61600
b100101010 %
b100101010 !
b100101010 *
b100110100 "
b100110100 $
b100110100 (
#61800
b100101011 %
b100101011 !
b100101011 *
b100110101 "
b100110101 $
b100110101 (
#62000
b100101100 %
b100101100 !
b100101100 *
b100110110 "
b100110110 $
b100110110 (
#62200
b100101101 %
b100101101 !
b100101101 *
b100110111 "
b100110111 $
b100110111 (
#62400
b100101110 %
b100101110 !
b100101110 *
b100111000 "
b100111000 $
b100111000 (
#62600
b100101111 %
b100101111 !
b100101111 *
b100111001 "
b100111001 $
b100111001 (
#62800
b100110000 %
b100110000 !
b100110000 *
b100111010 "
b100111010 $
b100111010 (
#63000
b100110001 %
b100110001 !
b100110001 *
b100111011 "
b100111011 $
b100111011 (
